[
  {
    "alias": "CIC",
    "name": "4BACREC"
  },
  {
    "alias": "CJC",
    "name": "4BACREP"
  },
  {
    "alias": "CHC",
    "name": "4BACREV"
  },
  {
    "alias": "CII",
    "name": "4BAHREC"
  },
  {
    "alias": "CJI",
    "name": "4BAHREP"
  },
  {
    "alias": "CHI",
    "name": "4BAHREV"
  },
  {
    "alias": "3VB",
    "name": "ABDETMOINS"
  },
  {
    "alias": "3VA",
    "name": "ABDETPLUS"
  },
  {
    "alias": "3VR",
    "name": "ABIMPMV"
  },
  {
    "alias": "3VQ",
    "name": "ABIMPPV"
  },
  {
    "alias": "3WD",
    "name": "ABPVNOSURSIS"
  },
  {
    "alias": "3WC",
    "name": "ABPVSURSIS"
  },
  {
    "alias": "0RA",
    "name": "ABSTELE"
  },
  {
    "alias": "9YI",
    "name": "ACODELAISINR"
  },
  {
    "alias": "8TV",
    "name": "ALLECS"
  },
  {
    "alias": "1CP",
    "name": "ALLO1"
  },
  {
    "alias": "1DP",
    "name": "ALLO2"
  },
  {
    "alias": "1EP",
    "name": "ALLO3"
  },
  {
    "alias": "1FP",
    "name": "ALLO4"
  },
  {
    "alias": "1BP",
    "name": "ALLOC"
  },
  {
    "alias": "1AP",
    "name": "ALLOV"
  },
  {
    "alias": "9YA",
    "name": "ANNUL2042"
  },
  {
    "alias": "5SN",
    "name": "ANOCEP"
  },
  {
    "alias": "5OS",
    "name": "ANOPEP"
  },
  {
    "alias": "5NS",
    "name": "ANOVEP"
  },
  {
    "alias": "AVIS",
    "name": "APPLI_AVIS"
  },
  {
    "alias": "V_COLBERT",
    "name": "APPLI_COLBERT"
  },
  {
    "alias": "V_OCEANS",
    "name": "APPLI_OCEANS"
  },
  {
    "alias": "7DL",
    "name": "ASCAPA"
  },
  {
    "alias": "5UB",
    "name": "AUTOBICPC"
  },
  {
    "alias": "5VB",
    "name": "AUTOBICPP"
  },
  {
    "alias": "5TB",
    "name": "AUTOBICPV"
  },
  {
    "alias": "5UA",
    "name": "AUTOBICVC"
  },
  {
    "alias": "5VA",
    "name": "AUTOBICVP"
  },
  {
    "alias": "5TA",
    "name": "AUTOBICVV"
  },
  {
    "alias": "5UE",
    "name": "AUTOBNCC"
  },
  {
    "alias": "5VE",
    "name": "AUTOBNCP"
  },
  {
    "alias": "5TE",
    "name": "AUTOBNCV"
  },
  {
    "alias": "8UY",
    "name": "AUTOVERSLIB"
  },
  {
    "alias": "8UX",
    "name": "AUTOVERSSUP"
  },
  {
    "alias": "8TT",
    "name": "AVETRAN"
  },
  {
    "alias": "5IE",
    "name": "BA1AC"
  },
  {
    "alias": "5JE",
    "name": "BA1AP"
  },
  {
    "alias": "5HE",
    "name": "BA1AV"
  },
  {
    "alias": "5IF",
    "name": "BACDEC"
  },
  {
    "alias": "5JF",
    "name": "BACDEP"
  },
  {
    "alias": "5HF",
    "name": "BACDEV"
  },
  {
    "alias": "5IC",
    "name": "BACREC"
  },
  {
    "alias": "5JC",
    "name": "BACREP"
  },
  {
    "alias": "5HC",
    "name": "BACREV"
  },
  {
    "alias": "5IB",
    "name": "BAEXC"
  },
  {
    "alias": "5JB",
    "name": "BAEXP"
  },
  {
    "alias": "5HB",
    "name": "BAEXV"
  },
  {
    "alias": "5IX",
    "name": "BAF1AC"
  },
  {
    "alias": "5JX",
    "name": "BAF1AP"
  },
  {
    "alias": "5HX",
    "name": "BAF1AV"
  },
  {
    "alias": "5IO",
    "name": "BAFC"
  },
  {
    "alias": "5ID",
    "name": "BAFORESTC"
  },
  {
    "alias": "5JD",
    "name": "BAFORESTP"
  },
  {
    "alias": "5HD",
    "name": "BAFORESTV"
  },
  {
    "alias": "5JO",
    "name": "BAFP"
  },
  {
    "alias": "5IW",
    "name": "BAFPVC"
  },
  {
    "alias": "5JW",
    "name": "BAFPVP"
  },
  {
    "alias": "5HW",
    "name": "BAFPVV"
  },
  {
    "alias": "5HO",
    "name": "BAFV"
  },
  {
    "alias": "5IL",
    "name": "BAHDEC"
  },
  {
    "alias": "5JL",
    "name": "BAHDEP"
  },
  {
    "alias": "5HL",
    "name": "BAHDEV"
  },
  {
    "alias": "5IH",
    "name": "BAHEXC"
  },
  {
    "alias": "5JH",
    "name": "BAHEXP"
  },
  {
    "alias": "5HH",
    "name": "BAHEXV"
  },
  {
    "alias": "5II",
    "name": "BAHREC"
  },
  {
    "alias": "5JI",
    "name": "BAHREP"
  },
  {
    "alias": "5HI",
    "name": "BAHREV"
  },
  {
    "alias": "4TQ",
    "name": "BAILOC98"
  },
  {
    "alias": "5IZ",
    "name": "BANOCGAC"
  },
  {
    "alias": "5JZ",
    "name": "BANOCGAP"
  },
  {
    "alias": "5HZ",
    "name": "BANOCGAV"
  },
  {
    "alias": "5IM",
    "name": "BAPERPC"
  },
  {
    "alias": "5JM",
    "name": "BAPERPP"
  },
  {
    "alias": "5HM",
    "name": "BAPERPV"
  },
  {
    "alias": "8YO",
    "name": "BASRET"
  },
  {
    "alias": "5LE",
    "name": "BI1AC"
  },
  {
    "alias": "5ME",
    "name": "BI1AP"
  },
  {
    "alias": "5KE",
    "name": "BI1AV"
  },
  {
    "alias": "5OE",
    "name": "BI2AC"
  },
  {
    "alias": "5PE",
    "name": "BI2AP"
  },
  {
    "alias": "5NE",
    "name": "BI2AV"
  },
  {
    "alias": "5OF",
    "name": "BICDEC"
  },
  {
    "alias": "5PF",
    "name": "BICDEP"
  },
  {
    "alias": "5NF",
    "name": "BICDEV"
  },
  {
    "alias": "5LF",
    "name": "BICDNC"
  },
  {
    "alias": "5MF",
    "name": "BICDNP"
  },
  {
    "alias": "5KF",
    "name": "BICDNV"
  },
  {
    "alias": "5LB",
    "name": "BICEXC"
  },
  {
    "alias": "5MB",
    "name": "BICEXP"
  },
  {
    "alias": "5KB",
    "name": "BICEXV"
  },
  {
    "alias": "5OL",
    "name": "BICHDEC"
  },
  {
    "alias": "5PL",
    "name": "BICHDEP"
  },
  {
    "alias": "5NL",
    "name": "BICHDEV"
  },
  {
    "alias": "5OI",
    "name": "BICHREC"
  },
  {
    "alias": "5PI",
    "name": "BICHREP"
  },
  {
    "alias": "5NI",
    "name": "BICHREV"
  },
  {
    "alias": "5LC",
    "name": "BICNOC"
  },
  {
    "alias": "5MC",
    "name": "BICNOP"
  },
  {
    "alias": "5KC",
    "name": "BICNOV"
  },
  {
    "alias": "5OB",
    "name": "BICNPEXC"
  },
  {
    "alias": "5PB",
    "name": "BICNPEXP"
  },
  {
    "alias": "5NB",
    "name": "BICNPEXV"
  },
  {
    "alias": "5OH",
    "name": "BICNPHEXC"
  },
  {
    "alias": "5PH",
    "name": "BICNPHEXP"
  },
  {
    "alias": "5NH",
    "name": "BICNPHEXV"
  },
  {
    "alias": "5LJ",
    "name": "BICPMVCTC"
  },
  {
    "alias": "5MJ",
    "name": "BICPMVCTP"
  },
  {
    "alias": "5KJ",
    "name": "BICPMVCTV"
  },
  {
    "alias": "5OC",
    "name": "BICREC"
  },
  {
    "alias": "5PC",
    "name": "BICREP"
  },
  {
    "alias": "5NC",
    "name": "BICREV"
  },
  {
    "alias": "9YJ",
    "name": "BIGREST"
  },
  {
    "alias": "5LL",
    "name": "BIHDNC"
  },
  {
    "alias": "5ML",
    "name": "BIHDNP"
  },
  {
    "alias": "5KL",
    "name": "BIHDNV"
  },
  {
    "alias": "5LH",
    "name": "BIHEXC"
  },
  {
    "alias": "5MH",
    "name": "BIHEXP"
  },
  {
    "alias": "5KH",
    "name": "BIHEXV"
  },
  {
    "alias": "5LI",
    "name": "BIHNOC"
  },
  {
    "alias": "5MI",
    "name": "BIHNOP"
  },
  {
    "alias": "5KI",
    "name": "BIHNOV"
  },
  {
    "alias": "5LS",
    "name": "BIPERPC"
  },
  {
    "alias": "5MS",
    "name": "BIPERPP"
  },
  {
    "alias": "5KS",
    "name": "BIPERPV"
  },
  {
    "alias": "5RD",
    "name": "BN1AC"
  },
  {
    "alias": "5SD",
    "name": "BN1AP"
  },
  {
    "alias": "5QD",
    "name": "BN1AV"
  },
  {
    "alias": "5RF",
    "name": "BNCAABC"
  },
  {
    "alias": "5SF",
    "name": "BNCAABP"
  },
  {
    "alias": "5JG",
    "name": "BNCAABV"
  },
  {
    "alias": "5RG",
    "name": "BNCAADC"
  },
  {
    "alias": "5SG",
    "name": "BNCAADP"
  },
  {
    "alias": "5JJ",
    "name": "BNCAADV"
  },
  {
    "alias": "5RL",
    "name": "BNCCRC"
  },
  {
    "alias": "5SW",
    "name": "BNCCRFC"
  },
  {
    "alias": "5SX",
    "name": "BNCCRFP"
  },
  {
    "alias": "5SV",
    "name": "BNCCRFV"
  },
  {
    "alias": "5SL",
    "name": "BNCCRP"
  },
  {
    "alias": "5QL",
    "name": "BNCCRV"
  },
  {
    "alias": "5RE",
    "name": "BNCDEC"
  },
  {
    "alias": "5SE",
    "name": "BNCDEP"
  },
  {
    "alias": "5QE",
    "name": "BNCDEV"
  },
  {
    "alias": "5RB",
    "name": "BNCEXC"
  },
  {
    "alias": "5SB",
    "name": "BNCEXP"
  },
  {
    "alias": "5QB",
    "name": "BNCEXV"
  },
  {
    "alias": "5LV",
    "name": "BNCNP1AC"
  },
  {
    "alias": "5MV",
    "name": "BNCNP1AP"
  },
  {
    "alias": "5KV",
    "name": "BNCNP1AV"
  },
  {
    "alias": "5LU",
    "name": "BNCNPC"
  },
  {
    "alias": "5JU",
    "name": "BNCNPDCT"
  },
  {
    "alias": "5LW",
    "name": "BNCNPDEC"
  },
  {
    "alias": "5MW",
    "name": "BNCNPDEP"
  },
  {
    "alias": "5KW",
    "name": "BNCNPDEV"
  },
  {
    "alias": "5MU",
    "name": "BNCNPP"
  },
  {
    "alias": "5LY",
    "name": "BNCNPPVC"
  },
  {
    "alias": "5MY",
    "name": "BNCNPPVP"
  },
  {
    "alias": "5KY",
    "name": "BNCNPPVV"
  },
  {
    "alias": "5JK",
    "name": "BNCNPREXAAC"
  },
  {
    "alias": "5LK",
    "name": "BNCNPREXAAP"
  },
  {
    "alias": "5HK",
    "name": "BNCNPREXAAV"
  },
  {
    "alias": "5KK",
    "name": "BNCNPREXC"
  },
  {
    "alias": "5MK",
    "name": "BNCNPREXP"
  },
  {
    "alias": "5IK",
    "name": "BNCNPREXV"
  },
  {
    "alias": "5KU",
    "name": "BNCNPV"
  },
  {
    "alias": "5LZ",
    "name": "BNCPMVCTC"
  },
  {
    "alias": "5MZ",
    "name": "BNCPMVCTP"
  },
  {
    "alias": "5KZ",
    "name": "BNCPMVCTV"
  },
  {
    "alias": "5IR",
    "name": "BNCPRO1AC"
  },
  {
    "alias": "5JR",
    "name": "BNCPRO1AP"
  },
  {
    "alias": "5HR",
    "name": "BNCPRO1AV"
  },
  {
    "alias": "5IQ",
    "name": "BNCPROC"
  },
  {
    "alias": "5IS",
    "name": "BNCPRODEC"
  },
  {
    "alias": "5JS",
    "name": "BNCPRODEP"
  },
  {
    "alias": "5HS",
    "name": "BNCPRODEV"
  },
  {
    "alias": "5IP",
    "name": "BNCPROEXC"
  },
  {
    "alias": "5JP",
    "name": "BNCPROEXP"
  },
  {
    "alias": "5HP",
    "name": "BNCPROEXV"
  },
  {
    "alias": "5JQ",
    "name": "BNCPROP"
  },
  {
    "alias": "5IV",
    "name": "BNCPROPVC"
  },
  {
    "alias": "5JV",
    "name": "BNCPROPVP"
  },
  {
    "alias": "5HV",
    "name": "BNCPROPVV"
  },
  {
    "alias": "5HQ",
    "name": "BNCPROV"
  },
  {
    "alias": "5RC",
    "name": "BNCREC"
  },
  {
    "alias": "5SC",
    "name": "BNCREP"
  },
  {
    "alias": "5QC",
    "name": "BNCREV"
  },
  {
    "alias": "5RK",
    "name": "BNHDEC"
  },
  {
    "alias": "5SK",
    "name": "BNHDEP"
  },
  {
    "alias": "5QK",
    "name": "BNHDEV"
  },
  {
    "alias": "5RH",
    "name": "BNHEXC"
  },
  {
    "alias": "5SH",
    "name": "BNHEXP"
  },
  {
    "alias": "5QH",
    "name": "BNHEXV"
  },
  {
    "alias": "5RI",
    "name": "BNHREC"
  },
  {
    "alias": "5SI",
    "name": "BNHREP"
  },
  {
    "alias": "5QI",
    "name": "BNHREV"
  },
  {
    "alias": "3SI",
    "name": "BPCOPTC"
  },
  {
    "alias": "3VI",
    "name": "BPCOPTV"
  },
  {
    "alias": "3VK",
    "name": "BPCOSAC"
  },
  {
    "alias": "3VJ",
    "name": "BPCOSAV"
  },
  {
    "alias": "3SD",
    "name": "BPV18C"
  },
  {
    "alias": "3VD",
    "name": "BPV18V"
  },
  {
    "alias": "3SF",
    "name": "BPV40C"
  },
  {
    "alias": "3VF",
    "name": "BPV40V"
  },
  {
    "alias": "3VL",
    "name": "BPVKRI"
  },
  {
    "alias": "3SS",
    "name": "BPVOPTCSC"
  },
  {
    "alias": "3VS",
    "name": "BPVOPTCSV"
  },
  {
    "alias": "3VG",
    "name": "BPVRCM"
  },
  {
    "alias": "3SJ",
    "name": "BPVSJ"
  },
  {
    "alias": "3SK",
    "name": "BPVSK"
  },
  {
    "alias": "8ZB",
    "name": "BRAS"
  },
  {
    "alias": "8YX",
    "name": "BULLRET"
  },
  {
    "alias": "RBS",
    "name": "CARPEC"
  },
  {
    "alias": "NBS",
    "name": "CARPENBAC"
  },
  {
    "alias": "NCS",
    "name": "CARPENBAP1"
  },
  {
    "alias": "NDS",
    "name": "CARPENBAP2"
  },
  {
    "alias": "NES",
    "name": "CARPENBAP3"
  },
  {
    "alias": "NFS",
    "name": "CARPENBAP4"
  },
  {
    "alias": "NAS",
    "name": "CARPENBAV"
  },
  {
    "alias": "RCS",
    "name": "CARPEP1"
  },
  {
    "alias": "RDS",
    "name": "CARPEP2"
  },
  {
    "alias": "RES",
    "name": "CARPEP3"
  },
  {
    "alias": "RFS",
    "name": "CARPEP4"
  },
  {
    "alias": "RAS",
    "name": "CARPEV"
  },
  {
    "alias": "RBJ",
    "name": "CARTSC"
  },
  {
    "alias": "NBJ",
    "name": "CARTSNBAC"
  },
  {
    "alias": "NCJ",
    "name": "CARTSNBAP1"
  },
  {
    "alias": "NDJ",
    "name": "CARTSNBAP2"
  },
  {
    "alias": "NEJ",
    "name": "CARTSNBAP3"
  },
  {
    "alias": "NFJ",
    "name": "CARTSNBAP4"
  },
  {
    "alias": "NAJ",
    "name": "CARTSNBAV"
  },
  {
    "alias": "RCJ",
    "name": "CARTSP1"
  },
  {
    "alias": "RDJ",
    "name": "CARTSP2"
  },
  {
    "alias": "REJ",
    "name": "CARTSP3"
  },
  {
    "alias": "RFJ",
    "name": "CARTSP4"
  },
  {
    "alias": "RAJ",
    "name": "CARTSV"
  },
  {
    "alias": "8TD",
    "name": "CASECHR"
  },
  {
    "alias": "7VO",
    "name": "CASEPRETUD"
  },
  {
    "alias": "8UU",
    "name": "CBETRAN"
  },
  {
    "alias": "8YW",
    "name": "CDISPROV"
  },
  {
    "alias": "7HJ",
    "name": "CELLIERHJ"
  },
  {
    "alias": "7HK",
    "name": "CELLIERHK"
  },
  {
    "alias": "7HL",
    "name": "CELLIERHL"
  },
  {
    "alias": "7HM",
    "name": "CELLIERHM"
  },
  {
    "alias": "7HN",
    "name": "CELLIERHN"
  },
  {
    "alias": "7HO",
    "name": "CELLIERHO"
  },
  {
    "alias": "7JA",
    "name": "CELLIERJA"
  },
  {
    "alias": "7JB",
    "name": "CELLIERJB"
  },
  {
    "alias": "7JD",
    "name": "CELLIERJD"
  },
  {
    "alias": "7JE",
    "name": "CELLIERJE"
  },
  {
    "alias": "7JF",
    "name": "CELLIERJF"
  },
  {
    "alias": "7JG",
    "name": "CELLIERJG"
  },
  {
    "alias": "7JH",
    "name": "CELLIERJH"
  },
  {
    "alias": "7JJ",
    "name": "CELLIERJJ"
  },
  {
    "alias": "7JK",
    "name": "CELLIERJK"
  },
  {
    "alias": "7JL",
    "name": "CELLIERJL"
  },
  {
    "alias": "7JM",
    "name": "CELLIERJM"
  },
  {
    "alias": "7JN",
    "name": "CELLIERJN"
  },
  {
    "alias": "7JO",
    "name": "CELLIERJO"
  },
  {
    "alias": "7JP",
    "name": "CELLIERJP"
  },
  {
    "alias": "7JQ",
    "name": "CELLIERJQ"
  },
  {
    "alias": "7JR",
    "name": "CELLIERJR"
  },
  {
    "alias": "7NA",
    "name": "CELLIERNA"
  },
  {
    "alias": "7NB",
    "name": "CELLIERNB"
  },
  {
    "alias": "7NC",
    "name": "CELLIERNC"
  },
  {
    "alias": "7ND",
    "name": "CELLIERND"
  },
  {
    "alias": "7NE",
    "name": "CELLIERNE"
  },
  {
    "alias": "7NF",
    "name": "CELLIERNF"
  },
  {
    "alias": "7NG",
    "name": "CELLIERNG"
  },
  {
    "alias": "7NH",
    "name": "CELLIERNH"
  },
  {
    "alias": "7NI",
    "name": "CELLIERNI"
  },
  {
    "alias": "7NJ",
    "name": "CELLIERNJ"
  },
  {
    "alias": "7NK",
    "name": "CELLIERNK"
  },
  {
    "alias": "7NL",
    "name": "CELLIERNL"
  },
  {
    "alias": "7NM",
    "name": "CELLIERNM"
  },
  {
    "alias": "7NN",
    "name": "CELLIERNN"
  },
  {
    "alias": "7NO",
    "name": "CELLIERNO"
  },
  {
    "alias": "7NP",
    "name": "CELLIERNP"
  },
  {
    "alias": "7NQ",
    "name": "CELLIERNQ"
  },
  {
    "alias": "7NR",
    "name": "CELLIERNR"
  },
  {
    "alias": "7NS",
    "name": "CELLIERNS"
  },
  {
    "alias": "7NT",
    "name": "CELLIERNT"
  },
  {
    "alias": "7HA",
    "name": "CELREPHA"
  },
  {
    "alias": "7HB",
    "name": "CELREPHB"
  },
  {
    "alias": "7HD",
    "name": "CELREPHD"
  },
  {
    "alias": "7HE",
    "name": "CELREPHE"
  },
  {
    "alias": "7HF",
    "name": "CELREPHF"
  },
  {
    "alias": "7HG",
    "name": "CELREPHG"
  },
  {
    "alias": "7HH",
    "name": "CELREPHH"
  },
  {
    "alias": "7HR",
    "name": "CELREPHR"
  },
  {
    "alias": "7HS",
    "name": "CELREPHS"
  },
  {
    "alias": "7HT",
    "name": "CELREPHT"
  },
  {
    "alias": "7HU",
    "name": "CELREPHU"
  },
  {
    "alias": "7HV",
    "name": "CELREPHV"
  },
  {
    "alias": "7HW",
    "name": "CELREPHW"
  },
  {
    "alias": "7HX",
    "name": "CELREPHX"
  },
  {
    "alias": "7HZ",
    "name": "CELREPHZ"
  },
  {
    "alias": "7LA",
    "name": "CELRREDLA"
  },
  {
    "alias": "7LB",
    "name": "CELRREDLB"
  },
  {
    "alias": "7LC",
    "name": "CELRREDLC"
  },
  {
    "alias": "7LD",
    "name": "CELRREDLD"
  },
  {
    "alias": "7LE",
    "name": "CELRREDLE"
  },
  {
    "alias": "7LF",
    "name": "CELRREDLF"
  },
  {
    "alias": "5RM",
    "name": "CESSASSC"
  },
  {
    "alias": "5QM",
    "name": "CESSASSV"
  },
  {
    "alias": "7SN",
    "name": "CHAUBOISN"
  },
  {
    "alias": "7SO",
    "name": "CHAUBOISO"
  },
  {
    "alias": "7SS",
    "name": "CHAUFSOL"
  },
  {
    "alias": "6GI",
    "name": "CHENF1"
  },
  {
    "alias": "6GJ",
    "name": "CHENF2"
  },
  {
    "alias": "6GK",
    "name": "CHENF3"
  },
  {
    "alias": "6GL",
    "name": "CHENF4"
  },
  {
    "alias": "6EV",
    "name": "CHNFAC"
  },
  {
    "alias": "6DD",
    "name": "CHRDED"
  },
  {
    "alias": "6EU",
    "name": "CHRFAC"
  },
  {
    "alias": "7UO",
    "name": "CIAQCUL"
  },
  {
    "alias": "7SD",
    "name": "CIBOIBAIL"
  },
  {
    "alias": "8TS",
    "name": "CICORSENOW"
  },
  {
    "alias": "8WV",
    "name": "CIDEBITTABAC"
  },
  {
    "alias": "7SH",
    "name": "CIDEP15"
  },
  {
    "alias": "8XP",
    "name": "CIIMPPRO"
  },
  {
    "alias": "8XQ",
    "name": "CIIMPPRO2"
  },
  {
    "alias": "8TG",
    "name": "CIINVCORSE"
  },
  {
    "alias": "7GN",
    "name": "CINE1"
  },
  {
    "alias": "7FN",
    "name": "CINE2"
  },
  {
    "alias": "7SG",
    "name": "CINRJ"
  },
  {
    "alias": "7SE",
    "name": "CINRJBAIL"
  },
  {
    "alias": "9YT",
    "name": "CMAJ"
  },
  {
    "alias": "V_CMAJ2",
    "name": "CMAJ2"
  },
  {
    "alias": "9XT",
    "name": "CMAJ_ISF"
  },
  {
    "alias": "9YZ",
    "name": "CO2044P"
  },
  {
    "alias": "9YH",
    "name": "CO2047"
  },
  {
    "alias": "9YG",
    "name": "CO2102"
  },
  {
    "alias": "8ZF",
    "name": "CO35"
  },
  {
    "alias": "9YF",
    "name": "CODCHA"
  },
  {
    "alias": "V_CODE_2042",
    "name": "CODE_2042"
  },
  {
    "alias": "9YK",
    "name": "CODSIR"
  },
  {
    "alias": "7LY",
    "name": "CONVCREA"
  },
  {
    "alias": "7MY",
    "name": "CONVHAND"
  },
  {
    "alias": "7AF",
    "name": "COSBC"
  },
  {
    "alias": "7AH",
    "name": "COSBP"
  },
  {
    "alias": "7AD",
    "name": "COSBV"
  },
  {
    "alias": "FCT",
    "name": "COTF1"
  },
  {
    "alias": "FDT",
    "name": "COTF2"
  },
  {
    "alias": "FET",
    "name": "COTF3"
  },
  {
    "alias": "FFT",
    "name": "COTF4"
  },
  {
    "alias": "FBT",
    "name": "COTFC"
  },
  {
    "alias": "7UL",
    "name": "COTFORET"
  },
  {
    "alias": "FAT",
    "name": "COTFV"
  },
  {
    "alias": "8ZJ",
    "name": "CRDSIM"
  },
  {
    "alias": "8WA",
    "name": "CREAGRIBIO"
  },
  {
    "alias": "7DB",
    "name": "CREAIDE"
  },
  {
    "alias": "8TZ",
    "name": "CREAPP"
  },
  {
    "alias": "8WR",
    "name": "CREARTS"
  },
  {
    "alias": "7WQ",
    "name": "CRECHOBAS"
  },
  {
    "alias": "7WK",
    "name": "CRECHOBOI"
  },
  {
    "alias": "7WH",
    "name": "CRECHOCON2"
  },
  {
    "alias": "8WT",
    "name": "CRECONGAGRI"
  },
  {
    "alias": "8UT",
    "name": "CREDPVREP"
  },
  {
    "alias": "8UZ",
    "name": "CREFAM"
  },
  {
    "alias": "8WD",
    "name": "CREFORMCHENT"
  },
  {
    "alias": "8WE",
    "name": "CREINTERESSE"
  },
  {
    "alias": "7SF",
    "name": "CRENRJ"
  },
  {
    "alias": "7WF",
    "name": "CRENRJRNOUV"
  },
  {
    "alias": "8WB",
    "name": "CREPROSP"
  },
  {
    "alias": "8WU",
    "name": "CRERESTAU"
  },
  {
    "alias": "8TE",
    "name": "CRIGA"
  },
  {
    "alias": "8YP",
    "name": "CSALPIRATE"
  },
  {
    "alias": "8YV",
    "name": "CSALPROV"
  },
  {
    "alias": "8ZL",
    "name": "CSGIM"
  },
  {
    "alias": "8YD",
    "name": "CSPROVYD"
  },
  {
    "alias": "8YE",
    "name": "CSPROVYE"
  },
  {
    "alias": "8YF",
    "name": "CSPROVYF"
  },
  {
    "alias": "8YG",
    "name": "CSPROVYG"
  },
  {
    "alias": "8YH",
    "name": "CSPROVYH"
  },
  {
    "alias": "3SN",
    "name": "CVNSALAC"
  },
  {
    "alias": "3VN",
    "name": "CVNSALAV"
  },
  {
    "alias": "5MT",
    "name": "DABNCNP1"
  },
  {
    "alias": "5LT",
    "name": "DABNCNP2"
  },
  {
    "alias": "5KT",
    "name": "DABNCNP3"
  },
  {
    "alias": "5JT",
    "name": "DABNCNP4"
  },
  {
    "alias": "5IT",
    "name": "DABNCNP5"
  },
  {
    "alias": "5HT",
    "name": "DABNCNP6"
  },
  {
    "alias": "5QQ",
    "name": "DAGRI1"
  },
  {
    "alias": "5QP",
    "name": "DAGRI2"
  },
  {
    "alias": "5QO",
    "name": "DAGRI3"
  },
  {
    "alias": "5QN",
    "name": "DAGRI4"
  },
  {
    "alias": "5QG",
    "name": "DAGRI5"
  },
  {
    "alias": "5QF",
    "name": "DAGRI6"
  },
  {
    "alias": "9YD",
    "name": "DATDEPETR"
  },
  {
    "alias": "DAT",
    "name": "DATOCEANS"
  },
  {
    "alias": "9YR",
    "name": "DATRETETR"
  },
  {
    "alias": "6DE",
    "name": "DCSG"
  },
  {
    "alias": "8ZM",
    "name": "DCSGIM"
  },
  {
    "alias": "6FL",
    "name": "DEFAA0"
  },
  {
    "alias": "6FE",
    "name": "DEFAA1"
  },
  {
    "alias": "6FD",
    "name": "DEFAA2"
  },
  {
    "alias": "6FC",
    "name": "DEFAA3"
  },
  {
    "alias": "6FB",
    "name": "DEFAA4"
  },
  {
    "alias": "6FA",
    "name": "DEFAA5"
  },
  {
    "alias": "5RW",
    "name": "DEFBIC1"
  },
  {
    "alias": "5RR",
    "name": "DEFBIC2"
  },
  {
    "alias": "5RQ",
    "name": "DEFBIC3"
  },
  {
    "alias": "5RP",
    "name": "DEFBIC4"
  },
  {
    "alias": "5RO",
    "name": "DEFBIC5"
  },
  {
    "alias": "5RN",
    "name": "DEFBIC6"
  },
  {
    "alias": "2AA",
    "name": "DEFRCM"
  },
  {
    "alias": "2AL",
    "name": "DEFRCM2"
  },
  {
    "alias": "2AM",
    "name": "DEFRCM3"
  },
  {
    "alias": "2AN",
    "name": "DEFRCM4"
  },
  {
    "alias": "2AQ",
    "name": "DEFRCM5"
  },
  {
    "alias": "2AR",
    "name": "DEFRCM6"
  },
  {
    "alias": "8ZU",
    "name": "DEFZU"
  },
  {
    "alias": "7WY",
    "name": "DEPCHOBAS"
  },
  {
    "alias": "7SZ",
    "name": "DEPENV"
  },
  {
    "alias": "7TT",
    "name": "DEPENVTT"
  },
  {
    "alias": "7TU",
    "name": "DEPENVTU"
  },
  {
    "alias": "7TV",
    "name": "DEPENVTV"
  },
  {
    "alias": "7TW",
    "name": "DEPENVTW"
  },
  {
    "alias": "7TX",
    "name": "DEPENVTX"
  },
  {
    "alias": "7TY",
    "name": "DEPENVTY"
  },
  {
    "alias": "7WZ",
    "name": "DEPMOBIL"
  },
  {
    "alias": "1CI",
    "name": "DETS1"
  },
  {
    "alias": "1DI",
    "name": "DETS2"
  },
  {
    "alias": "1EI",
    "name": "DETS3"
  },
  {
    "alias": "1FI",
    "name": "DETS4"
  },
  {
    "alias": "1BI",
    "name": "DETSC"
  },
  {
    "alias": "1AI",
    "name": "DETSV"
  },
  {
    "alias": "7SV",
    "name": "DIAGPERF"
  },
  {
    "alias": "2BG",
    "name": "DIREPARGNE"
  },
  {
    "alias": "RTS",
    "name": "DISQUO"
  },
  {
    "alias": "NTS",
    "name": "DISQUONB"
  },
  {
    "alias": "8ZY",
    "name": "DMOND"
  },
  {
    "alias": "5SP",
    "name": "DNOCEP"
  },
  {
    "alias": "5NU",
    "name": "DNOCEPC"
  },
  {
    "alias": "5OU",
    "name": "DNOCEPP"
  },
  {
    "alias": "7VC",
    "name": "DONAUTRE"
  },
  {
    "alias": "7VA",
    "name": "DONETRAN"
  },
  {
    "alias": "3VH",
    "name": "DPVRCM"
  },
  {
    "alias": "7SU",
    "name": "EAUPLUV"
  },
  {
    "alias": "7SM",
    "name": "ELESOL"
  },
  {
    "alias": "8CY",
    "name": "ELURASC"
  },
  {
    "alias": "8BY",
    "name": "ELURASV"
  },
  {
    "alias": "7ST",
    "name": "ENERGIEST"
  },
  {
    "alias": "8ZZ",
    "name": "ESFP"
  },
  {
    "alias": "9ZU",
    "name": "EXCLUAMIABLE"
  },
  {
    "alias": "1DN",
    "name": "EXOCETC"
  },
  {
    "alias": "1SM",
    "name": "EXOCETV"
  },
  {
    "alias": "7GQ",
    "name": "FCPI"
  },
  {
    "alias": "5IN",
    "name": "FEXC"
  },
  {
    "alias": "5JN",
    "name": "FEXP"
  },
  {
    "alias": "5HN",
    "name": "FEXV"
  },
  {
    "alias": "7FQ",
    "name": "FFIP"
  },
  {
    "alias": "7FM",
    "name": "FIPCORSE"
  },
  {
    "alias": "7FL",
    "name": "FIPDOMCOM"
  },
  {
    "alias": "V_FLAG_1731",
    "name": "FLAG_1731"
  },
  {
    "alias": "V_FLAG_9XT",
    "name": "FLAG_9XT"
  },
  {
    "alias": "V_FLAG_9YT",
    "name": "FLAG_9YT"
  },
  {
    "alias": "V_FLAG_ACO",
    "name": "FLAG_ACO"
  },
  {
    "alias": "V_FLAG_DEFAU",
    "name": "FLAG_DEFAUT"
  },
  {
    "alias": "V_FLAG_NINR",
    "name": "FLAG_NINR"
  },
  {
    "alias": "V_FLAG_PRIM",
    "name": "FLAG_PRIM"
  },
  {
    "alias": "V_FLAG_RECTF",
    "name": "FLAG_RECTIF"
  },
  {
    "alias": "V_FLAG_RETA",
    "name": "FLAG_RETARD"
  },
  {
    "alias": "V_FLAG_TRTAF",
    "name": "FLAG_TRTARDIF"
  },
  {
    "alias": "RBA",
    "name": "FONCI"
  },
  {
    "alias": "NBA",
    "name": "FONCINB"
  },
  {
    "alias": "7UC",
    "name": "FORET"
  },
  {
    "alias": "1CK",
    "name": "FRN1"
  },
  {
    "alias": "1DK",
    "name": "FRN2"
  },
  {
    "alias": "1EK",
    "name": "FRN3"
  },
  {
    "alias": "1FK",
    "name": "FRN4"
  },
  {
    "alias": "1BK",
    "name": "FRNC"
  },
  {
    "alias": "1AK",
    "name": "FRNV"
  },
  {
    "alias": "3VC",
    "name": "GAINABDET"
  },
  {
    "alias": "3VT",
    "name": "GAINPEA"
  },
  {
    "alias": "3SO",
    "name": "GAINSALAC"
  },
  {
    "alias": "3VO",
    "name": "GAINSALAV"
  },
  {
    "alias": "1UV",
    "name": "GLD1C"
  },
  {
    "alias": "1TV",
    "name": "GLD1V"
  },
  {
    "alias": "1UW",
    "name": "GLD2C"
  },
  {
    "alias": "1TW",
    "name": "GLD2V"
  },
  {
    "alias": "1UX",
    "name": "GLD3C"
  },
  {
    "alias": "1TX",
    "name": "GLD3V"
  },
  {
    "alias": "1UT",
    "name": "GLDGRATC"
  },
  {
    "alias": "1TT",
    "name": "GLDGRATV"
  },
  {
    "alias": "1OY",
    "name": "GSALC"
  },
  {
    "alias": "1NY",
    "name": "GSALV"
  },
  {
    "alias": "1BU",
    "name": "HEURESUPC"
  },
  {
    "alias": "1CU",
    "name": "HEURESUPP1"
  },
  {
    "alias": "1DU",
    "name": "HEURESUPP2"
  },
  {
    "alias": "1ET",
    "name": "HEURESUPP3"
  },
  {
    "alias": "1FT",
    "name": "HEURESUPP4"
  },
  {
    "alias": "1AU",
    "name": "HEURESUPV"
  },
  {
    "alias": "V_IAN_DERSTT",
    "name": "IAN_DERSTTR"
  },
  {
    "alias": "8YI",
    "name": "IMPRET"
  },
  {
    "alias": "7DG",
    "name": "INAIDE"
  },
  {
    "alias": "8TW",
    "name": "INDECS"
  },
  {
    "alias": "ZZB",
    "name": "INDJNONIMPC"
  },
  {
    "alias": "ZZA",
    "name": "INDJNONIMPV"
  },
  {
    "alias": "7XD",
    "name": "INDLOCNEUF"
  },
  {
    "alias": "7XE",
    "name": "INDLOCRES"
  },
  {
    "alias": "3WY",
    "name": "INDPVSURSI"
  },
  {
    "alias": "3WZ",
    "name": "INDPVSURSI2"
  },
  {
    "alias": "8ZK",
    "name": "IND_TDR"
  },
  {
    "alias": "V_IND_TL_MF",
    "name": "IND_TL_MF"
  },
  {
    "alias": "7UM",
    "name": "INTDIFAGRI"
  },
  {
    "alias": "RTR",
    "name": "INTERE"
  },
  {
    "alias": "NTR",
    "name": "INTERENB"
  },
  {
    "alias": "7QI",
    "name": "INVDIR2009"
  },
  {
    "alias": "7QF",
    "name": "INVDOMRET50"
  },
  {
    "alias": "7QG",
    "name": "INVDOMRET60"
  },
  {
    "alias": "7QE",
    "name": "INVENDEB2009"
  },
  {
    "alias": "7KS",
    "name": "INVENDI"
  },
  {
    "alias": "5UC",
    "name": "INVENTC"
  },
  {
    "alias": "5VC",
    "name": "INVENTP"
  },
  {
    "alias": "5TC",
    "name": "INVENTV"
  },
  {
    "alias": "7QR",
    "name": "INVIMP"
  },
  {
    "alias": "7QL",
    "name": "INVLGAUTRE"
  },
  {
    "alias": "7QT",
    "name": "INVLGDEB"
  },
  {
    "alias": "7QC",
    "name": "INVLGDEB2009"
  },
  {
    "alias": "7QM",
    "name": "INVLGDEB2010"
  },
  {
    "alias": "7XK",
    "name": "INVLOCHOTR"
  },
  {
    "alias": "7XO",
    "name": "INVLOCHOTR1"
  },
  {
    "alias": "7XC",
    "name": "INVLOCNEUF"
  },
  {
    "alias": "7XL",
    "name": "INVLOCRES"
  },
  {
    "alias": "7XG",
    "name": "INVLOCT1"
  },
  {
    "alias": "7XA",
    "name": "INVLOCT1AV"
  },
  {
    "alias": "7XH",
    "name": "INVLOCT2"
  },
  {
    "alias": "7XB",
    "name": "INVLOCT2AV"
  },
  {
    "alias": "7XN",
    "name": "INVLOCXN"
  },
  {
    "alias": "7XV",
    "name": "INVLOCXV"
  },
  {
    "alias": "7XX",
    "name": "INVLOCXX"
  },
  {
    "alias": "7XZ",
    "name": "INVLOCXZ"
  },
  {
    "alias": "7QB",
    "name": "INVLOG2008"
  },
  {
    "alias": "7QD",
    "name": "INVLOG2009"
  },
  {
    "alias": "7XR",
    "name": "INVLOGHOT"
  },
  {
    "alias": "7XQ",
    "name": "INVLOGREHA"
  },
  {
    "alias": "7QK",
    "name": "INVLOGSOC"
  },
  {
    "alias": "7IN",
    "name": "INVNPROF1"
  },
  {
    "alias": "7IV",
    "name": "INVNPROF2"
  },
  {
    "alias": "7IR",
    "name": "INVNPROREP"
  },
  {
    "alias": "7KT",
    "name": "INVOMENTKT"
  },
  {
    "alias": "7KU",
    "name": "INVOMENTKU"
  },
  {
    "alias": "7MN",
    "name": "INVOMENTMN"
  },
  {
    "alias": "7NU",
    "name": "INVOMENTNU"
  },
  {
    "alias": "7NV",
    "name": "INVOMENTNV"
  },
  {
    "alias": "7NW",
    "name": "INVOMENTNW"
  },
  {
    "alias": "7NX",
    "name": "INVOMENTNX"
  },
  {
    "alias": "7NY",
    "name": "INVOMENTNY"
  },
  {
    "alias": "7RG",
    "name": "INVOMENTRG"
  },
  {
    "alias": "7RH",
    "name": "INVOMENTRH"
  },
  {
    "alias": "7RI",
    "name": "INVOMENTRI"
  },
  {
    "alias": "7RJ",
    "name": "INVOMENTRJ"
  },
  {
    "alias": "7RK",
    "name": "INVOMENTRK"
  },
  {
    "alias": "7RL",
    "name": "INVOMENTRL"
  },
  {
    "alias": "7RM",
    "name": "INVOMENTRM"
  },
  {
    "alias": "7RN",
    "name": "INVOMENTRN"
  },
  {
    "alias": "7RO",
    "name": "INVOMENTRO"
  },
  {
    "alias": "7RP",
    "name": "INVOMENTRP"
  },
  {
    "alias": "7RQ",
    "name": "INVOMENTRQ"
  },
  {
    "alias": "7RR",
    "name": "INVOMENTRR"
  },
  {
    "alias": "7RS",
    "name": "INVOMENTRS"
  },
  {
    "alias": "7RT",
    "name": "INVOMENTRT"
  },
  {
    "alias": "7RU",
    "name": "INVOMENTRU"
  },
  {
    "alias": "7RV",
    "name": "INVOMENTRV"
  },
  {
    "alias": "7RW",
    "name": "INVOMENTRW"
  },
  {
    "alias": "7RX",
    "name": "INVOMENTRX"
  },
  {
    "alias": "7RY",
    "name": "INVOMENTRY"
  },
  {
    "alias": "7OA",
    "name": "INVOMLOGOA"
  },
  {
    "alias": "7OB",
    "name": "INVOMLOGOB"
  },
  {
    "alias": "7OC",
    "name": "INVOMLOGOC"
  },
  {
    "alias": "7OH",
    "name": "INVOMLOGOH"
  },
  {
    "alias": "7OI",
    "name": "INVOMLOGOI"
  },
  {
    "alias": "7OJ",
    "name": "INVOMLOGOJ"
  },
  {
    "alias": "7OK",
    "name": "INVOMLOGOK"
  },
  {
    "alias": "7OL",
    "name": "INVOMLOGOL"
  },
  {
    "alias": "7OM",
    "name": "INVOMLOGOM"
  },
  {
    "alias": "7ON",
    "name": "INVOMLOGON"
  },
  {
    "alias": "7OO",
    "name": "INVOMLOGOO"
  },
  {
    "alias": "7OP",
    "name": "INVOMLOGOP"
  },
  {
    "alias": "7OQ",
    "name": "INVOMLOGOQ"
  },
  {
    "alias": "7OR",
    "name": "INVOMLOGOR"
  },
  {
    "alias": "7OS",
    "name": "INVOMLOGOS"
  },
  {
    "alias": "7OT",
    "name": "INVOMLOGOT"
  },
  {
    "alias": "7OU",
    "name": "INVOMLOGOU"
  },
  {
    "alias": "7OV",
    "name": "INVOMLOGOV"
  },
  {
    "alias": "7OW",
    "name": "INVOMLOGOW"
  },
  {
    "alias": "7QV",
    "name": "INVOMQV"
  },
  {
    "alias": "7MM",
    "name": "INVOMREP"
  },
  {
    "alias": "7PA",
    "name": "INVOMRETPA"
  },
  {
    "alias": "7PB",
    "name": "INVOMRETPB"
  },
  {
    "alias": "7PD",
    "name": "INVOMRETPD"
  },
  {
    "alias": "7PE",
    "name": "INVOMRETPE"
  },
  {
    "alias": "7PF",
    "name": "INVOMRETPF"
  },
  {
    "alias": "7PH",
    "name": "INVOMRETPH"
  },
  {
    "alias": "7PI",
    "name": "INVOMRETPI"
  },
  {
    "alias": "7PJ",
    "name": "INVOMRETPJ"
  },
  {
    "alias": "7PL",
    "name": "INVOMRETPL"
  },
  {
    "alias": "7PM",
    "name": "INVOMRETPM"
  },
  {
    "alias": "7PN",
    "name": "INVOMRETPN"
  },
  {
    "alias": "7PO",
    "name": "INVOMRETPO"
  },
  {
    "alias": "7PP",
    "name": "INVOMRETPP"
  },
  {
    "alias": "7PQ",
    "name": "INVOMRETPQ"
  },
  {
    "alias": "7PR",
    "name": "INVOMRETPR"
  },
  {
    "alias": "7PS",
    "name": "INVOMRETPS"
  },
  {
    "alias": "7PT",
    "name": "INVOMRETPT"
  },
  {
    "alias": "7PU",
    "name": "INVOMRETPU"
  },
  {
    "alias": "7PV",
    "name": "INVOMRETPV"
  },
  {
    "alias": "7PW",
    "name": "INVOMRETPW"
  },
  {
    "alias": "7PX",
    "name": "INVOMRETPX"
  },
  {
    "alias": "7PY",
    "name": "INVOMRETPY"
  },
  {
    "alias": "7KH",
    "name": "INVOMSOCKH"
  },
  {
    "alias": "7KI",
    "name": "INVOMSOCKI"
  },
  {
    "alias": "7QJ",
    "name": "INVOMSOCQJ"
  },
  {
    "alias": "7QS",
    "name": "INVOMSOCQS"
  },
  {
    "alias": "7QU",
    "name": "INVOMSOCQU"
  },
  {
    "alias": "7QW",
    "name": "INVOMSOCQW"
  },
  {
    "alias": "7QX",
    "name": "INVOMSOCQX"
  },
  {
    "alias": "7IT",
    "name": "INVREDMEU"
  },
  {
    "alias": "7IP",
    "name": "INVREPMEU"
  },
  {
    "alias": "7IQ",
    "name": "INVREPNPRO"
  },
  {
    "alias": "7QO",
    "name": "INVRETRO1"
  },
  {
    "alias": "7QP",
    "name": "INVRETRO2"
  },
  {
    "alias": "7QN",
    "name": "INVSOC2010"
  },
  {
    "alias": "7KG",
    "name": "INVSOCNRET"
  },
  {
    "alias": "8TK",
    "name": "IPBOCH"
  },
  {
    "alias": "8TC",
    "name": "IPCHER"
  },
  {
    "alias": "8TH",
    "name": "IPELUS"
  },
  {
    "alias": "8TI",
    "name": "IPMOND"
  },
  {
    "alias": "8TU",
    "name": "IPPNCS"
  },
  {
    "alias": "8TP",
    "name": "IPPRICORSE"
  },
  {
    "alias": "8TB",
    "name": "IPRECH"
  },
  {
    "alias": "8TF",
    "name": "IPREP"
  },
  {
    "alias": "8TO",
    "name": "IPREPCORSE"
  },
  {
    "alias": "8TA",
    "name": "IPSOUR"
  },
  {
    "alias": "8TJ",
    "name": "IPSUIS"
  },
  {
    "alias": "8TY",
    "name": "IPSUISC"
  },
  {
    "alias": "8TN",
    "name": "IPSURSI"
  },
  {
    "alias": "8ZX",
    "name": "IPSURV"
  },
  {
    "alias": "8ZN",
    "name": "IPTEFN"
  },
  {
    "alias": "8ZR",
    "name": "IPTEFP"
  },
  {
    "alias": "8TM",
    "name": "IPTXMO"
  },
  {
    "alias": "8ZH",
    "name": "IPVLOC"
  },
  {
    "alias": "8ZG",
    "name": "IRANT"
  },
  {
    "alias": "9HI",
    "name": "ISFBASE"
  },
  {
    "alias": "9GL",
    "name": "ISFCONCUB"
  },
  {
    "alias": "9NG",
    "name": "ISFDONEURO"
  },
  {
    "alias": "9NC",
    "name": "ISFDONF"
  },
  {
    "alias": "9RS",
    "name": "ISFETRANG"
  },
  {
    "alias": "9NA",
    "name": "ISFFCPI"
  },
  {
    "alias": "9MX",
    "name": "ISFFIP"
  },
  {
    "alias": "9GM",
    "name": "ISFPART"
  },
  {
    "alias": "9PV",
    "name": "ISFPLAF"
  },
  {
    "alias": "9NE",
    "name": "ISFPMEDI"
  },
  {
    "alias": "9NF",
    "name": "ISFPMEIN"
  },
  {
    "alias": "9FG",
    "name": "ISFVBPAT"
  },
  {
    "alias": "9GY",
    "name": "ISF_LIMINF"
  },
  {
    "alias": "9GZ",
    "name": "ISF_LIMSUP"
  },
  {
    "alias": "7WA",
    "name": "ISOMURWA"
  },
  {
    "alias": "7WB",
    "name": "ISOMURWB"
  },
  {
    "alias": "7VE",
    "name": "ISOTOIVE"
  },
  {
    "alias": "7VF",
    "name": "ISOTOIVF"
  },
  {
    "alias": "5GJ",
    "name": "LNPRODEF1"
  },
  {
    "alias": "5GA",
    "name": "LNPRODEF10"
  },
  {
    "alias": "5GI",
    "name": "LNPRODEF2"
  },
  {
    "alias": "5GH",
    "name": "LNPRODEF3"
  },
  {
    "alias": "5GG",
    "name": "LNPRODEF4"
  },
  {
    "alias": "5GF",
    "name": "LNPRODEF5"
  },
  {
    "alias": "5GE",
    "name": "LNPRODEF6"
  },
  {
    "alias": "5GD",
    "name": "LNPRODEF7"
  },
  {
    "alias": "5GC",
    "name": "LNPRODEF8"
  },
  {
    "alias": "5GB",
    "name": "LNPRODEF9"
  },
  {
    "alias": "5OZ",
    "name": "LOCDEFNPC"
  },
  {
    "alias": "5OY",
    "name": "LOCDEFNPCGAC"
  },
  {
    "alias": "5PY",
    "name": "LOCDEFNPCGAPAC"
  },
  {
    "alias": "5NY",
    "name": "LOCDEFNPCGAV"
  },
  {
    "alias": "5PZ",
    "name": "LOCDEFNPPAC"
  },
  {
    "alias": "5NZ",
    "name": "LOCDEFNPV"
  },
  {
    "alias": "5RJ",
    "name": "LOCDEFPROC"
  },
  {
    "alias": "5RA",
    "name": "LOCDEFPROCGAC"
  },
  {
    "alias": "5SA",
    "name": "LOCDEFPROCGAP"
  },
  {
    "alias": "5QA",
    "name": "LOCDEFPROCGAV"
  },
  {
    "alias": "5SJ",
    "name": "LOCDEFPROP"
  },
  {
    "alias": "5QJ",
    "name": "LOCDEFPROV"
  },
  {
    "alias": "5OJ",
    "name": "LOCGITC"
  },
  {
    "alias": "5OM",
    "name": "LOCGITCC"
  },
  {
    "alias": "5PM",
    "name": "LOCGITCP"
  },
  {
    "alias": "5NM",
    "name": "LOCGITCV"
  },
  {
    "alias": "5LM",
    "name": "LOCGITHCC"
  },
  {
    "alias": "5MM",
    "name": "LOCGITHCP"
  },
  {
    "alias": "5KM",
    "name": "LOCGITHCV"
  },
  {
    "alias": "5PJ",
    "name": "LOCGITP"
  },
  {
    "alias": "5NJ",
    "name": "LOCGITV"
  },
  {
    "alias": "7IA",
    "name": "LOCMEUBIA"
  },
  {
    "alias": "7IB",
    "name": "LOCMEUBIB"
  },
  {
    "alias": "7IC",
    "name": "LOCMEUBIC"
  },
  {
    "alias": "7ID",
    "name": "LOCMEUBID"
  },
  {
    "alias": "7IE",
    "name": "LOCMEUBIE"
  },
  {
    "alias": "7IF",
    "name": "LOCMEUBIF"
  },
  {
    "alias": "7IG",
    "name": "LOCMEUBIG"
  },
  {
    "alias": "7IH",
    "name": "LOCMEUBIH"
  },
  {
    "alias": "7II",
    "name": "LOCMEUBII"
  },
  {
    "alias": "7IX",
    "name": "LOCMEUBIX"
  },
  {
    "alias": "7IZ",
    "name": "LOCMEUBIZ"
  },
  {
    "alias": "5OK",
    "name": "LOCNPC"
  },
  {
    "alias": "5OA",
    "name": "LOCNPCGAC"
  },
  {
    "alias": "5PA",
    "name": "LOCNPCGAPAC"
  },
  {
    "alias": "5NA",
    "name": "LOCNPCGAV"
  },
  {
    "alias": "5PK",
    "name": "LOCNPPAC"
  },
  {
    "alias": "5NK",
    "name": "LOCNPV"
  },
  {
    "alias": "5LA",
    "name": "LOCPROC"
  },
  {
    "alias": "5IA",
    "name": "LOCPROCGAC"
  },
  {
    "alias": "5JA",
    "name": "LOCPROCGAP"
  },
  {
    "alias": "5HA",
    "name": "LOCPROCGAV"
  },
  {
    "alias": "5MA",
    "name": "LOCPROP"
  },
  {
    "alias": "5KA",
    "name": "LOCPROV"
  },
  {
    "alias": "7IJ",
    "name": "LOCRESINEUV"
  },
  {
    "alias": "4BH",
    "name": "LOYELEV"
  },
  {
    "alias": "4BF",
    "name": "LOYIMP"
  },
  {
    "alias": "7SI",
    "name": "MATISOSI"
  },
  {
    "alias": "7SJ",
    "name": "MATISOSJ"
  },
  {
    "alias": "7IL",
    "name": "MEUBLENP"
  },
  {
    "alias": "5LQ",
    "name": "MIB1AC"
  },
  {
    "alias": "5MQ",
    "name": "MIB1AP"
  },
  {
    "alias": "5KQ",
    "name": "MIB1AV"
  },
  {
    "alias": "5LR",
    "name": "MIBDEC"
  },
  {
    "alias": "5MR",
    "name": "MIBDEP"
  },
  {
    "alias": "5KR",
    "name": "MIBDEV"
  },
  {
    "alias": "5LN",
    "name": "MIBEXC"
  },
  {
    "alias": "5MN",
    "name": "MIBEXP"
  },
  {
    "alias": "5KN",
    "name": "MIBEXV"
  },
  {
    "alias": "5OG",
    "name": "MIBGITEC"
  },
  {
    "alias": "5PG",
    "name": "MIBGITEP"
  },
  {
    "alias": "5NG",
    "name": "MIBGITEV"
  },
  {
    "alias": "5OD",
    "name": "MIBMEUC"
  },
  {
    "alias": "5PD",
    "name": "MIBMEUP"
  },
  {
    "alias": "5ND",
    "name": "MIBMEUV"
  },
  {
    "alias": "5OQ",
    "name": "MIBNP1AC"
  },
  {
    "alias": "5PQ",
    "name": "MIBNP1AP"
  },
  {
    "alias": "5NQ",
    "name": "MIBNP1AV"
  },
  {
    "alias": "5IU",
    "name": "MIBNPDCT"
  },
  {
    "alias": "5OR",
    "name": "MIBNPDEC"
  },
  {
    "alias": "5PR",
    "name": "MIBNPDEP"
  },
  {
    "alias": "5NR",
    "name": "MIBNPDEV"
  },
  {
    "alias": "5ON",
    "name": "MIBNPEXC"
  },
  {
    "alias": "5PN",
    "name": "MIBNPEXP"
  },
  {
    "alias": "5NN",
    "name": "MIBNPEXV"
  },
  {
    "alias": "5OP",
    "name": "MIBNPPRESC"
  },
  {
    "alias": "5PP",
    "name": "MIBNPPRESP"
  },
  {
    "alias": "5NP",
    "name": "MIBNPPRESV"
  },
  {
    "alias": "5OX",
    "name": "MIBNPPVC"
  },
  {
    "alias": "5PX",
    "name": "MIBNPPVP"
  },
  {
    "alias": "5NX",
    "name": "MIBNPPVV"
  },
  {
    "alias": "5OO",
    "name": "MIBNPVENC"
  },
  {
    "alias": "5PO",
    "name": "MIBNPVENP"
  },
  {
    "alias": "5NO",
    "name": "MIBNPVENV"
  },
  {
    "alias": "5LP",
    "name": "MIBPRESC"
  },
  {
    "alias": "5MP",
    "name": "MIBPRESP"
  },
  {
    "alias": "5KP",
    "name": "MIBPRESV"
  },
  {
    "alias": "5LX",
    "name": "MIBPVC"
  },
  {
    "alias": "5MX",
    "name": "MIBPVP"
  },
  {
    "alias": "5KX",
    "name": "MIBPVV"
  },
  {
    "alias": "5LO",
    "name": "MIBVENC"
  },
  {
    "alias": "5MO",
    "name": "MIBVENP"
  },
  {
    "alias": "5KO",
    "name": "MIBVENV"
  },
  {
    "alias": "9YU",
    "name": "MOISAN"
  },
  {
    "alias": "V_MOISAN2",
    "name": "MOISAN2"
  },
  {
    "alias": "9XU",
    "name": "MOISAN_ISF"
  },
  {
    "alias": "7FG",
    "name": "NBACT"
  },
  {
    "alias": "6EL",
    "name": "NCHENF1"
  },
  {
    "alias": "6EM",
    "name": "NCHENF2"
  },
  {
    "alias": "6EN",
    "name": "NCHENF3"
  },
  {
    "alias": "6EQ",
    "name": "NCHENF4"
  },
  {
    "alias": "8ZO",
    "name": "NRBASE"
  },
  {
    "alias": "7MA",
    "name": "NRETROC40"
  },
  {
    "alias": "7LG",
    "name": "NRETROC50"
  },
  {
    "alias": "8ZI",
    "name": "NRINET"
  },
  {
    "alias": "6CB",
    "name": "NUPROP"
  },
  {
    "alias": "7QA",
    "name": "OPTPLAF15"
  },
  {
    "alias": "6GU",
    "name": "PAAP"
  },
  {
    "alias": "6GP",
    "name": "PAAV"
  },
  {
    "alias": "1CO",
    "name": "PALI1"
  },
  {
    "alias": "1DO",
    "name": "PALI2"
  },
  {
    "alias": "1EO",
    "name": "PALI3"
  },
  {
    "alias": "1FO",
    "name": "PALI4"
  },
  {
    "alias": "1BO",
    "name": "PALIC"
  },
  {
    "alias": "1AO",
    "name": "PALIV"
  },
  {
    "alias": "7WS",
    "name": "PARVITWS"
  },
  {
    "alias": "7KA",
    "name": "PATNAT"
  },
  {
    "alias": "7KB",
    "name": "PATNAT1"
  },
  {
    "alias": "7KC",
    "name": "PATNAT2"
  },
  {
    "alias": "1BT",
    "name": "PCAPTAXC"
  },
  {
    "alias": "1AT",
    "name": "PCAPTAXV"
  },
  {
    "alias": "3VM",
    "name": "PEA"
  },
  {
    "alias": "FCS",
    "name": "PEBF1"
  },
  {
    "alias": "FDS",
    "name": "PEBF2"
  },
  {
    "alias": "FES",
    "name": "PEBF3"
  },
  {
    "alias": "FFS",
    "name": "PEBF4"
  },
  {
    "alias": "FBS",
    "name": "PEBFC"
  },
  {
    "alias": "FAS",
    "name": "PEBFV"
  },
  {
    "alias": "8TX",
    "name": "PENECS"
  },
  {
    "alias": "RBO",
    "name": "PENSALC"
  },
  {
    "alias": "NBO",
    "name": "PENSALNBC"
  },
  {
    "alias": "NCO",
    "name": "PENSALNBP1"
  },
  {
    "alias": "NDO",
    "name": "PENSALNBP2"
  },
  {
    "alias": "NEO",
    "name": "PENSALNBP3"
  },
  {
    "alias": "NFO",
    "name": "PENSALNBP4"
  },
  {
    "alias": "NAO",
    "name": "PENSALNBV"
  },
  {
    "alias": "RCO",
    "name": "PENSALP1"
  },
  {
    "alias": "RDO",
    "name": "PENSALP2"
  },
  {
    "alias": "REO",
    "name": "PENSALP3"
  },
  {
    "alias": "RFO",
    "name": "PENSALP4"
  },
  {
    "alias": "RAO",
    "name": "PENSALV"
  },
  {
    "alias": "6QT",
    "name": "PERPC"
  },
  {
    "alias": "6QW",
    "name": "PERPIMPATRIE"
  },
  {
    "alias": "6QR",
    "name": "PERPMUTU"
  },
  {
    "alias": "6QU",
    "name": "PERPP"
  },
  {
    "alias": "APT",
    "name": "PERPPLAFCC"
  },
  {
    "alias": "APU",
    "name": "PERPPLAFCP"
  },
  {
    "alias": "APS",
    "name": "PERPPLAFCV"
  },
  {
    "alias": "DPT",
    "name": "PERPPLAFNUC1"
  },
  {
    "alias": "CPT",
    "name": "PERPPLAFNUC2"
  },
  {
    "alias": "BPT",
    "name": "PERPPLAFNUC3"
  },
  {
    "alias": "DPU",
    "name": "PERPPLAFNUP1"
  },
  {
    "alias": "CPU",
    "name": "PERPPLAFNUP2"
  },
  {
    "alias": "BPU",
    "name": "PERPPLAFNUP3"
  },
  {
    "alias": "DPS",
    "name": "PERPPLAFNUV1"
  },
  {
    "alias": "CPS",
    "name": "PERPPLAFNUV2"
  },
  {
    "alias": "BPS",
    "name": "PERPPLAFNUV3"
  },
  {
    "alias": "6QS",
    "name": "PERPV"
  },
  {
    "alias": "6RT",
    "name": "PERP_COTC"
  },
  {
    "alias": "6RU",
    "name": "PERP_COTP"
  },
  {
    "alias": "6RS",
    "name": "PERP_COTV"
  },
  {
    "alias": "7CU",
    "name": "PETIPRISE"
  },
  {
    "alias": "6PT",
    "name": "PLAF_PERPC"
  },
  {
    "alias": "6PU",
    "name": "PLAF_PERPP"
  },
  {
    "alias": "6PS",
    "name": "PLAF_PERPV"
  },
  {
    "alias": "7SP",
    "name": "POMPESP"
  },
  {
    "alias": "7SQ",
    "name": "POMPESQ"
  },
  {
    "alias": "7SR",
    "name": "POMPESR"
  },
  {
    "alias": "7SL",
    "name": "PORENT"
  },
  {
    "alias": "7WW",
    "name": "PORTEWW"
  },
  {
    "alias": "7WX",
    "name": "PORTEWX"
  },
  {
    "alias": "5OW",
    "name": "PPEACC"
  },
  {
    "alias": "5PW",
    "name": "PPEACP"
  },
  {
    "alias": "5NW",
    "name": "PPEACV"
  },
  {
    "alias": "8YY",
    "name": "PPEISFPIR"
  },
  {
    "alias": "1BV",
    "name": "PPENHC"
  },
  {
    "alias": "1CV",
    "name": "PPENHP1"
  },
  {
    "alias": "1DV",
    "name": "PPENHP2"
  },
  {
    "alias": "1QV",
    "name": "PPENHP3"
  },
  {
    "alias": "1RV",
    "name": "PPENHP4"
  },
  {
    "alias": "1AV",
    "name": "PPENHV"
  },
  {
    "alias": "5OV",
    "name": "PPENJC"
  },
  {
    "alias": "5PV",
    "name": "PPENJP"
  },
  {
    "alias": "5NV",
    "name": "PPENJV"
  },
  {
    "alias": "8YZ",
    "name": "PPEREVPRO"
  },
  {
    "alias": "1BX",
    "name": "PPETPC"
  },
  {
    "alias": "1CX",
    "name": "PPETPP1"
  },
  {
    "alias": "1DX",
    "name": "PPETPP2"
  },
  {
    "alias": "1QX",
    "name": "PPETPP3"
  },
  {
    "alias": "1RX",
    "name": "PPETPP4"
  },
  {
    "alias": "1AX",
    "name": "PPETPV"
  },
  {
    "alias": "2EE",
    "name": "PPLIB"
  },
  {
    "alias": "1CS",
    "name": "PRBR1"
  },
  {
    "alias": "1DS",
    "name": "PRBR2"
  },
  {
    "alias": "1ES",
    "name": "PRBR3"
  },
  {
    "alias": "1FS",
    "name": "PRBR4"
  },
  {
    "alias": "1BS",
    "name": "PRBRC"
  },
  {
    "alias": "1AS",
    "name": "PRBRV"
  },
  {
    "alias": "7VX",
    "name": "PREHABT"
  },
  {
    "alias": "7VY",
    "name": "PREHABT1"
  },
  {
    "alias": "7VZ",
    "name": "PREHABT2"
  },
  {
    "alias": "7VW",
    "name": "PREHABTN"
  },
  {
    "alias": "7VU",
    "name": "PREHABTN1"
  },
  {
    "alias": "7VV",
    "name": "PREHABTN2"
  },
  {
    "alias": "7VT",
    "name": "PREHABTVT"
  },
  {
    "alias": "8XT",
    "name": "PRELIBXT"
  },
  {
    "alias": "7DQ",
    "name": "PREMAIDE"
  },
  {
    "alias": "8VX",
    "name": "PREREV"
  },
  {
    "alias": "7WN",
    "name": "PRESCOMP2000"
  },
  {
    "alias": "7WO",
    "name": "PRESCOMPJUGE"
  },
  {
    "alias": "8WC",
    "name": "PRESINTER"
  },
  {
    "alias": "7UK",
    "name": "PRETUD"
  },
  {
    "alias": "7TD",
    "name": "PRETUDANT"
  },
  {
    "alias": "8ZP",
    "name": "PRODOM"
  },
  {
    "alias": "8ZV",
    "name": "PROGUY"
  },
  {
    "alias": "RCH",
    "name": "PROVIE"
  },
  {
    "alias": "NCH",
    "name": "PROVIENB"
  },
  {
    "alias": "8ZS",
    "name": "PRSPROV"
  },
  {
    "alias": "7WE",
    "name": "PTZDEVDUR"
  },
  {
    "alias": "7WG",
    "name": "PTZDEVDURN"
  },
  {
    "alias": "3SA",
    "name": "PVDIRTAX"
  },
  {
    "alias": "3VW",
    "name": "PVEXOSEC"
  },
  {
    "alias": "3VZ",
    "name": "PVIMMO"
  },
  {
    "alias": "3WB",
    "name": "PVIMPOS"
  },
  {
    "alias": "5NT",
    "name": "PVINCE"
  },
  {
    "alias": "5OT",
    "name": "PVINPE"
  },
  {
    "alias": "5SO",
    "name": "PVINVE"
  },
  {
    "alias": "3VP",
    "name": "PVJEUNENT"
  },
  {
    "alias": "3SE",
    "name": "PVMOBNR"
  },
  {
    "alias": "3VY",
    "name": "PVPART"
  },
  {
    "alias": "3VX",
    "name": "PVREP8"
  },
  {
    "alias": "3WH",
    "name": "PVREPORT"
  },
  {
    "alias": "5IG",
    "name": "PVSOCC"
  },
  {
    "alias": "5HG",
    "name": "PVSOCV"
  },
  {
    "alias": "3WA",
    "name": "PVSURSI"
  },
  {
    "alias": "3WF",
    "name": "PVSURSIWF"
  },
  {
    "alias": "3WG",
    "name": "PVSURSIWG"
  },
  {
    "alias": "3SB",
    "name": "PVTAXSB"
  },
  {
    "alias": "3SC",
    "name": "PVTAXSC"
  },
  {
    "alias": "3WE",
    "name": "PVTITRESOC"
  },
  {
    "alias": "8WW",
    "name": "R1649"
  },
  {
    "alias": "6ST",
    "name": "RACCOTC"
  },
  {
    "alias": "6SU",
    "name": "RACCOTP"
  },
  {
    "alias": "6SS",
    "name": "RACCOTV"
  },
  {
    "alias": "7CE",
    "name": "RCCURE"
  },
  {
    "alias": "2DC",
    "name": "RCMABD"
  },
  {
    "alias": "2CH",
    "name": "RCMAV"
  },
  {
    "alias": "2AB",
    "name": "RCMAVFT"
  },
  {
    "alias": "2CA",
    "name": "RCMFR"
  },
  {
    "alias": "2TR",
    "name": "RCMHAB"
  },
  {
    "alias": "2TS",
    "name": "RCMHAD"
  },
  {
    "alias": "2DM",
    "name": "RCMIMPAT"
  },
  {
    "alias": "2DH",
    "name": "RCMLIB"
  },
  {
    "alias": "2DA",
    "name": "RCMLIBDIV"
  },
  {
    "alias": "2CG",
    "name": "RCMRDS"
  },
  {
    "alias": "2BH",
    "name": "RCMSOC"
  },
  {
    "alias": "2FU",
    "name": "RCMTNC"
  },
  {
    "alias": "5IY",
    "name": "RCSC"
  },
  {
    "alias": "5JY",
    "name": "RCSP"
  },
  {
    "alias": "5HY",
    "name": "RCSV"
  },
  {
    "alias": "7FF",
    "name": "RDCOM"
  },
  {
    "alias": "7UF",
    "name": "RDDOUP"
  },
  {
    "alias": "7EC",
    "name": "RDENL"
  },
  {
    "alias": "7ED",
    "name": "RDENLQAR"
  },
  {
    "alias": "7EA",
    "name": "RDENS"
  },
  {
    "alias": "7EB",
    "name": "RDENSQAR"
  },
  {
    "alias": "7EF",
    "name": "RDENU"
  },
  {
    "alias": "7EG",
    "name": "RDENUQAR"
  },
  {
    "alias": "7WJ",
    "name": "RDEQPAHA"
  },
  {
    "alias": "7VD",
    "name": "RDFDAUTRE"
  },
  {
    "alias": "7VB",
    "name": "RDFDONETR"
  },
  {
    "alias": "7UG",
    "name": "RDFDOU"
  },
  {
    "alias": "7UN",
    "name": "RDFOREST"
  },
  {
    "alias": "7UQ",
    "name": "RDFORESTGES"
  },
  {
    "alias": "7UP",
    "name": "RDFORESTRA"
  },
  {
    "alias": "7UE",
    "name": "RDFREP"
  },
  {
    "alias": "7GA",
    "name": "RDGARD1"
  },
  {
    "alias": "7GE",
    "name": "RDGARD1QAR"
  },
  {
    "alias": "7GB",
    "name": "RDGARD2"
  },
  {
    "alias": "7GF",
    "name": "RDGARD2QAR"
  },
  {
    "alias": "7GC",
    "name": "RDGARD3"
  },
  {
    "alias": "7GG",
    "name": "RDGARD3QAR"
  },
  {
    "alias": "7GD",
    "name": "RDGARD4"
  },
  {
    "alias": "7GM",
    "name": "RDGARD4QAR"
  },
  {
    "alias": "7WI",
    "name": "RDGEQ"
  },
  {
    "alias": "7US",
    "name": "RDMECENAT"
  },
  {
    "alias": "7WP",
    "name": "RDPRESREPORT"
  },
  {
    "alias": "7UD",
    "name": "RDREP"
  },
  {
    "alias": "7GZ",
    "name": "RDRESU"
  },
  {
    "alias": "7CF",
    "name": "RDSNO"
  },
  {
    "alias": "7AE",
    "name": "RDSYCJ"
  },
  {
    "alias": "7AG",
    "name": "RDSYPP"
  },
  {
    "alias": "7AC",
    "name": "RDSYVO"
  },
  {
    "alias": "7WL",
    "name": "RDTECH"
  },
  {
    "alias": "8VV",
    "name": "RE168"
  },
  {
    "alias": "SBA",
    "name": "REAMOR"
  },
  {
    "alias": "TBA",
    "name": "REAMORNB"
  },
  {
    "alias": "7IS",
    "name": "REDMEUBLE"
  },
  {
    "alias": "7IU",
    "name": "REDREPNPRO"
  },
  {
    "alias": "8XR",
    "name": "REGCI"
  },
  {
    "alias": "2GO",
    "name": "REGPRIV"
  },
  {
    "alias": "RBP",
    "name": "REMPLAC"
  },
  {
    "alias": "NBP",
    "name": "REMPLANBC"
  },
  {
    "alias": "NCP",
    "name": "REMPLANBP1"
  },
  {
    "alias": "NDP",
    "name": "REMPLANBP2"
  },
  {
    "alias": "NEP",
    "name": "REMPLANBP3"
  },
  {
    "alias": "NFP",
    "name": "REMPLANBP4"
  },
  {
    "alias": "NAP",
    "name": "REMPLANBV"
  },
  {
    "alias": "RCP",
    "name": "REMPLAP1"
  },
  {
    "alias": "RDP",
    "name": "REMPLAP2"
  },
  {
    "alias": "REP",
    "name": "REMPLAP3"
  },
  {
    "alias": "RFP",
    "name": "REMPLAP4"
  },
  {
    "alias": "RAP",
    "name": "REMPLAV"
  },
  {
    "alias": "RAW",
    "name": "RENTAX"
  },
  {
    "alias": "RBW",
    "name": "RENTAX5"
  },
  {
    "alias": "RCW",
    "name": "RENTAX6"
  },
  {
    "alias": "RDW",
    "name": "RENTAX7"
  },
  {
    "alias": "NAW",
    "name": "RENTAXNB"
  },
  {
    "alias": "NBW",
    "name": "RENTAXNB5"
  },
  {
    "alias": "NCW",
    "name": "RENTAXNB6"
  },
  {
    "alias": "NDW",
    "name": "RENTAXNB7"
  },
  {
    "alias": "7XS",
    "name": "REPDON03"
  },
  {
    "alias": "7XT",
    "name": "REPDON04"
  },
  {
    "alias": "7XU",
    "name": "REPDON05"
  },
  {
    "alias": "7XW",
    "name": "REPDON06"
  },
  {
    "alias": "7XY",
    "name": "REPDON07"
  },
  {
    "alias": "7UU",
    "name": "REPFOR"
  },
  {
    "alias": "7UV",
    "name": "REPFOR1"
  },
  {
    "alias": "7UW",
    "name": "REPFOR2"
  },
  {
    "alias": "6HK",
    "name": "REPGROREP1"
  },
  {
    "alias": "6HL",
    "name": "REPGROREP11"
  },
  {
    "alias": "6HJ",
    "name": "REPGROREP2"
  },
  {
    "alias": "7PZ",
    "name": "REPINVDOMPRO2"
  },
  {
    "alias": "7QZ",
    "name": "REPINVDOMPRO3"
  },
  {
    "alias": "7XF",
    "name": "REPINVLOCINV"
  },
  {
    "alias": "7XM",
    "name": "REPINVLOCREA"
  },
  {
    "alias": "7XP",
    "name": "REPINVTOU"
  },
  {
    "alias": "7IK",
    "name": "REPMEUBLE"
  },
  {
    "alias": "7TE",
    "name": "REPSINFOR"
  },
  {
    "alias": "7TF",
    "name": "REPSINFOR1"
  },
  {
    "alias": "7TG",
    "name": "REPSINFOR2"
  },
  {
    "alias": "7CN",
    "name": "REPSNO1"
  },
  {
    "alias": "7CM",
    "name": "REPSNO2"
  },
  {
    "alias": "7CL",
    "name": "REPSNO3"
  },
  {
    "alias": "7CQ",
    "name": "REPSNON"
  },
  {
    "alias": "6GH",
    "name": "REPSOF"
  },
  {
    "alias": "7SW",
    "name": "RESCHAL"
  },
  {
    "alias": "7IW",
    "name": "RESIVIANT"
  },
  {
    "alias": "7IM",
    "name": "RESIVIEU"
  },
  {
    "alias": "7RA",
    "name": "RESTIMOPPAU"
  },
  {
    "alias": "7RB",
    "name": "RESTIMOSAUV"
  },
  {
    "alias": "RGO",
    "name": "RESTUC"
  },
  {
    "alias": "NGO",
    "name": "RESTUCNB"
  },
  {
    "alias": "7LH",
    "name": "RETROCOMLH"
  },
  {
    "alias": "7LI",
    "name": "RETROCOMLI"
  },
  {
    "alias": "7MB",
    "name": "RETROCOMMB"
  },
  {
    "alias": "7MC",
    "name": "RETROCOMMC"
  },
  {
    "alias": "RDC",
    "name": "REVACT"
  },
  {
    "alias": "NDC",
    "name": "REVACTNB"
  },
  {
    "alias": "8XA",
    "name": "REVCSXA"
  },
  {
    "alias": "8XB",
    "name": "REVCSXB"
  },
  {
    "alias": "8XC",
    "name": "REVCSXC"
  },
  {
    "alias": "8XD",
    "name": "REVCSXD"
  },
  {
    "alias": "8XE",
    "name": "REVCSXE"
  },
  {
    "alias": "8FV",
    "name": "REVFONC"
  },
  {
    "alias": "8ZC",
    "name": "REVMAR1"
  },
  {
    "alias": "8ZD",
    "name": "REVMAR2"
  },
  {
    "alias": "8ZE",
    "name": "REVMAR3"
  },
  {
    "alias": "RFU",
    "name": "REVPEA"
  },
  {
    "alias": "NFU",
    "name": "REVPEANB"
  },
  {
    "alias": "4BD",
    "name": "RFDANT"
  },
  {
    "alias": "4BC",
    "name": "RFDHIS"
  },
  {
    "alias": "4BB",
    "name": "RFDORD"
  },
  {
    "alias": "4BE",
    "name": "RFMIC"
  },
  {
    "alias": "4BA",
    "name": "RFORDI"
  },
  {
    "alias": "8YB",
    "name": "RFRH1"
  },
  {
    "alias": "8YA",
    "name": "RFRH2"
  },
  {
    "alias": "8YS",
    "name": "RFRN2"
  },
  {
    "alias": "8YR",
    "name": "RFRN3"
  },
  {
    "alias": "4BY",
    "name": "RFROBOR"
  },
  {
    "alias": "7RC",
    "name": "RIMOPPAUANT"
  },
  {
    "alias": "7RE",
    "name": "RIMOPPAURE"
  },
  {
    "alias": "7RD",
    "name": "RIMOSAUVANT"
  },
  {
    "alias": "7RF",
    "name": "RIMOSAUVRF"
  },
  {
    "alias": "7XI",
    "name": "RINVLOCINV"
  },
  {
    "alias": "7XJ",
    "name": "RINVLOCREA"
  },
  {
    "alias": "7NZ",
    "name": "RIRENOV"
  },
  {
    "alias": "7WR",
    "name": "RISKTEC"
  },
  {
    "alias": "8ZW",
    "name": "RMOND"
  },
  {
    "alias": "1BL",
    "name": "RSAFOYER"
  },
  {
    "alias": "1CB",
    "name": "RSAPAC1"
  },
  {
    "alias": "1DQ",
    "name": "RSAPAC2"
  },
  {
    "alias": "7FH",
    "name": "RSOCREPRISE"
  },
  {
    "alias": "7DD",
    "name": "RVAIDAS"
  },
  {
    "alias": "7DF",
    "name": "RVAIDE"
  },
  {
    "alias": "1AW",
    "name": "RVB1"
  },
  {
    "alias": "1BW",
    "name": "RVB2"
  },
  {
    "alias": "1CW",
    "name": "RVB3"
  },
  {
    "alias": "1DW",
    "name": "RVB4"
  },
  {
    "alias": "7CD",
    "name": "RVCURE"
  },
  {
    "alias": "8TQ",
    "name": "SALECS"
  },
  {
    "alias": "8TR",
    "name": "SALECSG"
  },
  {
    "alias": "1UY",
    "name": "SALINTC"
  },
  {
    "alias": "1TY",
    "name": "SALINTV"
  },
  {
    "alias": "7UT",
    "name": "SINISFORET"
  },
  {
    "alias": "7WM",
    "name": "SUBSTITRENTE"
  },
  {
    "alias": "8VW",
    "name": "TAX1649"
  },
  {
    "alias": "V_TAXAISO_DE",
    "name": "TAXAISO_DERSTTR"
  },
  {
    "alias": "8YC",
    "name": "TEFFHRC"
  },
  {
    "alias": "7WC",
    "name": "TRAMURWC"
  },
  {
    "alias": "7VG",
    "name": "TRATOIVG"
  },
  {
    "alias": "7WT",
    "name": "TRAVITWT"
  },
  {
    "alias": "0XX",
    "name": "TREVEX"
  },
  {
    "alias": "1BQ",
    "name": "TSASSUC"
  },
  {
    "alias": "1AQ",
    "name": "TSASSUV"
  },
  {
    "alias": "1MZ",
    "name": "TSELUPPEC"
  },
  {
    "alias": "1LZ",
    "name": "TSELUPPEV"
  },
  {
    "alias": "1CJ",
    "name": "TSHALLO1"
  },
  {
    "alias": "1DJ",
    "name": "TSHALLO2"
  },
  {
    "alias": "1EJ",
    "name": "TSHALLO3"
  },
  {
    "alias": "1FJ",
    "name": "TSHALLO4"
  },
  {
    "alias": "1BJ",
    "name": "TSHALLOC"
  },
  {
    "alias": "1AJ",
    "name": "TSHALLOV"
  },
  {
    "alias": "8ZA",
    "name": "VALREGCO"
  },
  {
    "alias": "7IO",
    "name": "VIEUMEUB"
  },
  {
    "alias": "7SK",
    "name": "VOLISO"
  },
  {
    "alias": "7WU",
    "name": "VOLISOWU"
  },
  {
    "alias": "7WV",
    "name": "VOLISOWV"
  },
  {
    "alias": "0AB",
    "name": "V_0AB"
  },
  {
    "alias": "0AC",
    "name": "V_0AC"
  },
  {
    "alias": "0AD",
    "name": "V_0AD"
  },
  {
    "alias": "0AE",
    "name": "V_0AE"
  },
  {
    "alias": "0AF",
    "name": "V_0AF"
  },
  {
    "alias": "0AG",
    "name": "V_0AG"
  },
  {
    "alias": "0AL",
    "name": "V_0AL"
  },
  {
    "alias": "0AM",
    "name": "V_0AM"
  },
  {
    "alias": "0AN",
    "name": "V_0AN"
  },
  {
    "alias": "0AO",
    "name": "V_0AO"
  },
  {
    "alias": "0AP",
    "name": "V_0AP"
  },
  {
    "alias": "0AS",
    "name": "V_0AS"
  },
  {
    "alias": "0AV",
    "name": "V_0AV"
  },
  {
    "alias": "0AW",
    "name": "V_0AW"
  },
  {
    "alias": "0AX",
    "name": "V_0AX"
  },
  {
    "alias": "0AY",
    "name": "V_0AY"
  },
  {
    "alias": "0AZ",
    "name": "V_0AZ"
  },
  {
    "alias": "0BT",
    "name": "V_0BT"
  },
  {
    "alias": "0CF",
    "name": "V_0CF"
  },
  {
    "alias": "0CG",
    "name": "V_0CG"
  },
  {
    "alias": "0CH",
    "name": "V_0CH"
  },
  {
    "alias": "0CI",
    "name": "V_0CI"
  },
  {
    "alias": "0CR",
    "name": "V_0CR"
  },
  {
    "alias": "0DA",
    "name": "V_0DA"
  },
  {
    "alias": "0DB",
    "name": "V_0DB"
  },
  {
    "alias": "0DJ",
    "name": "V_0DJ"
  },
  {
    "alias": "0DN",
    "name": "V_0DN"
  },
  {
    "alias": "0DP",
    "name": "V_0DP"
  },
  {
    "alias": "0F0",
    "name": "V_0F0"
  },
  {
    "alias": "0F1",
    "name": "V_0F1"
  },
  {
    "alias": "0F2",
    "name": "V_0F2"
  },
  {
    "alias": "0F3",
    "name": "V_0F3"
  },
  {
    "alias": "0F4",
    "name": "V_0F4"
  },
  {
    "alias": "0F5",
    "name": "V_0F5"
  },
  {
    "alias": "0F6",
    "name": "V_0F6"
  },
  {
    "alias": "0F7",
    "name": "V_0F7"
  },
  {
    "alias": "0G0",
    "name": "V_0G0"
  },
  {
    "alias": "0G1",
    "name": "V_0G1"
  },
  {
    "alias": "0G2",
    "name": "V_0G2"
  },
  {
    "alias": "0G3",
    "name": "V_0G3"
  },
  {
    "alias": "0G4",
    "name": "V_0G4"
  },
  {
    "alias": "0H0",
    "name": "V_0H0"
  },
  {
    "alias": "0H1",
    "name": "V_0H1"
  },
  {
    "alias": "0H2",
    "name": "V_0H2"
  },
  {
    "alias": "0H3",
    "name": "V_0H3"
  },
  {
    "alias": "0H4",
    "name": "V_0H4"
  },
  {
    "alias": "0H5",
    "name": "V_0H5"
  },
  {
    "alias": "0I0",
    "name": "V_0I0"
  },
  {
    "alias": "0I1",
    "name": "V_0I1"
  },
  {
    "alias": "0I2",
    "name": "V_0I2"
  },
  {
    "alias": "0I3",
    "name": "V_0I3"
  },
  {
    "alias": "0J0",
    "name": "V_0J0"
  },
  {
    "alias": "0J1",
    "name": "V_0J1"
  },
  {
    "alias": "0J2",
    "name": "V_0J2"
  },
  {
    "alias": "0J3",
    "name": "V_0J3"
  },
  {
    "alias": "0J4",
    "name": "V_0J4"
  },
  {
    "alias": "0J5",
    "name": "V_0J5"
  },
  {
    "alias": "0N0",
    "name": "V_0N0"
  },
  {
    "alias": "0N1",
    "name": "V_0N1"
  },
  {
    "alias": "0N2",
    "name": "V_0N2"
  },
  {
    "alias": "0N3",
    "name": "V_0N3"
  },
  {
    "alias": "0N4",
    "name": "V_0N4"
  },
  {
    "alias": "0N5",
    "name": "V_0N5"
  },
  {
    "alias": "0P0",
    "name": "V_0P0"
  },
  {
    "alias": "0P1",
    "name": "V_0P1"
  },
  {
    "alias": "0P2",
    "name": "V_0P2"
  },
  {
    "alias": "0P3",
    "name": "V_0P3"
  },
  {
    "alias": "0R0",
    "name": "V_0R0"
  },
  {
    "alias": "0R1",
    "name": "V_0R1"
  },
  {
    "alias": "0R2",
    "name": "V_0R2"
  },
  {
    "alias": "0R3",
    "name": "V_0R3"
  },
  {
    "alias": "0R4",
    "name": "V_0R4"
  },
  {
    "alias": "0SA",
    "name": "V_0SA"
  },
  {
    "alias": "0TA",
    "name": "V_0TA"
  },
  {
    "alias": "0VA",
    "name": "V_0VA"
  },
  {
    "alias": "8ZT",
    "name": "V_8ZT"
  },
  {
    "alias": "9XX",
    "name": "V_9XX"
  },
  {
    "alias": "A10R",
    "name": "V_A10REEL"
  },
  {
    "alias": "A11R",
    "name": "V_A11REEL"
  },
  {
    "alias": "A12R",
    "name": "V_A12REEL"
  },
  {
    "alias": "ACO_CIREL",
    "name": "V_ACO_CIREL"
  },
  {
    "alias": "ACO_MTAP",
    "name": "V_ACO_MTAP"
  },
  {
    "alias": "ANCSDED",
    "name": "V_ANCSDED"
  },
  {
    "alias": "ANC_BAR",
    "name": "V_ANC_BAR"
  },
  {
    "alias": "ANC_NAP",
    "name": "V_ANC_NAP"
  },
  {
    "alias": "ANREV",
    "name": "V_ANREV"
  },
  {
    "alias": "ANTCR",
    "name": "V_ANTCR"
  },
  {
    "alias": "ANTIR",
    "name": "V_ANTIR"
  },
  {
    "alias": "ANTISF",
    "name": "V_ANTISF"
  },
  {
    "alias": "ANTRE",
    "name": "V_ANTRE"
  },
  {
    "alias": "ANTREIR",
    "name": "V_ANTREIR"
  },
  {
    "alias": "AVFISCOPBIS",
    "name": "V_AVFISCOPBIS"
  },
  {
    "alias": "BCSG3",
    "name": "V_BCSG3"
  },
  {
    "alias": "BPRS3",
    "name": "V_BPRS3"
  },
  {
    "alias": "BRDS3",
    "name": "V_BRDS3"
  },
  {
    "alias": "BT0AC",
    "name": "V_BT0AC"
  },
  {
    "alias": "BT0AD",
    "name": "V_BT0AD"
  },
  {
    "alias": "BT0AE",
    "name": "V_BT0AE"
  },
  {
    "alias": "BT0AM",
    "name": "V_BT0AM"
  },
  {
    "alias": "BT0AO",
    "name": "V_BT0AO"
  },
  {
    "alias": "BT0AV",
    "name": "V_BT0AV"
  },
  {
    "alias": "BT0AX",
    "name": "V_BT0AX"
  },
  {
    "alias": "BT0CF",
    "name": "V_BT0CF"
  },
  {
    "alias": "BT0CH",
    "name": "V_BT0CH"
  },
  {
    "alias": "BT0F0",
    "name": "V_BT0F0"
  },
  {
    "alias": "BT0F1",
    "name": "V_BT0F1"
  },
  {
    "alias": "BT0F2",
    "name": "V_BT0F2"
  },
  {
    "alias": "BT0F3",
    "name": "V_BT0F3"
  },
  {
    "alias": "BT0F4",
    "name": "V_BT0F4"
  },
  {
    "alias": "BT0F5",
    "name": "V_BT0F5"
  },
  {
    "alias": "BT0H0",
    "name": "V_BT0H0"
  },
  {
    "alias": "BT0H1",
    "name": "V_BT0H1"
  },
  {
    "alias": "BT0H2",
    "name": "V_BT0H2"
  },
  {
    "alias": "BT0H3",
    "name": "V_BT0H3"
  },
  {
    "alias": "BT0H4",
    "name": "V_BT0H4"
  },
  {
    "alias": "BT0H5",
    "name": "V_BT0H5"
  },
  {
    "alias": "BTANC",
    "name": "V_BTANC"
  },
  {
    "alias": "BTBAILOC98",
    "name": "V_BTBAILOC98"
  },
  {
    "alias": "BTBNCDF",
    "name": "V_BTBNCDF"
  },
  {
    "alias": "BTCO2044P",
    "name": "V_BTCO2044P"
  },
  {
    "alias": "BTCREPROSP",
    "name": "V_BTCREPROSP"
  },
  {
    "alias": "BTCSGDED",
    "name": "V_BTCSGDED"
  },
  {
    "alias": "BTDBA",
    "name": "V_BTDBA"
  },
  {
    "alias": "BTDEFNPLOC",
    "name": "V_BTDEFNPLOC"
  },
  {
    "alias": "BTDEVDUR",
    "name": "V_BTDEVDUR"
  },
  {
    "alias": "BTDFRCM1",
    "name": "V_BTDFRCM1"
  },
  {
    "alias": "BTDFRCM2",
    "name": "V_BTDFRCM2"
  },
  {
    "alias": "BTDFRCM3",
    "name": "V_BTDFRCM3"
  },
  {
    "alias": "BTDFRCM4",
    "name": "V_BTDFRCM4"
  },
  {
    "alias": "BTDFRCM5",
    "name": "V_BTDFRCM5"
  },
  {
    "alias": "BTDFRCM6",
    "name": "V_BTDFRCM6"
  },
  {
    "alias": "BTDOMEX1",
    "name": "V_BTDOMEX1"
  },
  {
    "alias": "BTDOMEX2",
    "name": "V_BTDOMEX2"
  },
  {
    "alias": "BTDONS1",
    "name": "V_BTDONS1"
  },
  {
    "alias": "BTDONS2",
    "name": "V_BTDONS2"
  },
  {
    "alias": "BTDONS3",
    "name": "V_BTDONS3"
  },
  {
    "alias": "BTDONS4",
    "name": "V_BTDONS4"
  },
  {
    "alias": "BTDONS5",
    "name": "V_BTDONS5"
  },
  {
    "alias": "BTEXDOM",
    "name": "V_BTEXDOM"
  },
  {
    "alias": "BTFOREST",
    "name": "V_BTFOREST"
  },
  {
    "alias": "BTGECUM",
    "name": "V_BTGECUM"
  },
  {
    "alias": "BTIMP",
    "name": "V_BTIMP"
  },
  {
    "alias": "BTIRF",
    "name": "V_BTIRF"
  },
  {
    "alias": "BTMUL",
    "name": "V_BTMUL"
  },
  {
    "alias": "BTNATIMP",
    "name": "V_BTNATIMP"
  },
  {
    "alias": "BTNBP1",
    "name": "V_BTNBP1"
  },
  {
    "alias": "BTNBP2",
    "name": "V_BTNBP2"
  },
  {
    "alias": "BTNI1",
    "name": "V_BTNI1"
  },
  {
    "alias": "BTNUREPAR",
    "name": "V_BTNUREPAR"
  },
  {
    "alias": "BTPATNAT",
    "name": "V_BTPATNAT"
  },
  {
    "alias": "BTPERPC",
    "name": "V_BTPERPC"
  },
  {
    "alias": "BTPERPIMP",
    "name": "V_BTPERPIMP"
  },
  {
    "alias": "BTPERPNUC1",
    "name": "V_BTPERPNUC1"
  },
  {
    "alias": "BTPERPNUC2",
    "name": "V_BTPERPNUC2"
  },
  {
    "alias": "BTPERPNUC3",
    "name": "V_BTPERPNUC3"
  },
  {
    "alias": "BTPERPNUP1",
    "name": "V_BTPERPNUP1"
  },
  {
    "alias": "BTPERPNUP2",
    "name": "V_BTPERPNUP2"
  },
  {
    "alias": "BTPERPNUP3",
    "name": "V_BTPERPNUP3"
  },
  {
    "alias": "BTPERPNUV1",
    "name": "V_BTPERPNUV1"
  },
  {
    "alias": "BTPERPNUV2",
    "name": "V_BTPERPNUV2"
  },
  {
    "alias": "BTPERPNUV3",
    "name": "V_BTPERPNUV3"
  },
  {
    "alias": "BTPERPP",
    "name": "V_BTPERPP"
  },
  {
    "alias": "BTPERPTOTC",
    "name": "V_BTPERPTOTC"
  },
  {
    "alias": "BTPERPTOTP",
    "name": "V_BTPERPTOTP"
  },
  {
    "alias": "BTPERPTOTV",
    "name": "V_BTPERPTOTV"
  },
  {
    "alias": "BTPERPV",
    "name": "V_BTPERPV"
  },
  {
    "alias": "BTPME1",
    "name": "V_BTPME1"
  },
  {
    "alias": "BTPME2",
    "name": "V_BTPME2"
  },
  {
    "alias": "BTPME3",
    "name": "V_BTPME3"
  },
  {
    "alias": "BTPME4",
    "name": "V_BTPME4"
  },
  {
    "alias": "BTPRESCOMP",
    "name": "V_BTPRESCOMP"
  },
  {
    "alias": "BTPRETUD",
    "name": "V_BTPRETUD"
  },
  {
    "alias": "BTPVREP",
    "name": "V_BTPVREP"
  },
  {
    "alias": "BTR4DOMPRO",
    "name": "V_BTR4DOMPRO"
  },
  {
    "alias": "BTR5DOMPRO",
    "name": "V_BTR5DOMPRO"
  },
  {
    "alias": "BTREPCHER",
    "name": "V_BTREPCHER"
  },
  {
    "alias": "BTREPKSU",
    "name": "V_BTREPKSU"
  },
  {
    "alias": "BTREPKT",
    "name": "V_BTREPKT"
  },
  {
    "alias": "BTREPLGI",
    "name": "V_BTREPLGI"
  },
  {
    "alias": "BTREPLH",
    "name": "V_BTREPLH"
  },
  {
    "alias": "BTREPMAC",
    "name": "V_BTREPMAC"
  },
  {
    "alias": "BTREPMB",
    "name": "V_BTREPMB"
  },
  {
    "alias": "BTREPMEU",
    "name": "V_BTREPMEU"
  },
  {
    "alias": "BTREPNEUV",
    "name": "V_BTREPNEUV"
  },
  {
    "alias": "BTREPPA",
    "name": "V_BTREPPA"
  },
  {
    "alias": "BTREPPB",
    "name": "V_BTREPPB"
  },
  {
    "alias": "BTREPPD",
    "name": "V_BTREPPD"
  },
  {
    "alias": "BTREPPE",
    "name": "V_BTREPPE"
  },
  {
    "alias": "BTREPPF",
    "name": "V_BTREPPF"
  },
  {
    "alias": "BTREPPH",
    "name": "V_BTREPPH"
  },
  {
    "alias": "BTREPPI",
    "name": "V_BTREPPI"
  },
  {
    "alias": "BTREPPJ",
    "name": "V_BTREPPJ"
  },
  {
    "alias": "BTREPPL",
    "name": "V_BTREPPL"
  },
  {
    "alias": "BTREPQE",
    "name": "V_BTREPQE"
  },
  {
    "alias": "BTREPQF",
    "name": "V_BTREPQF"
  },
  {
    "alias": "BTREPQG",
    "name": "V_BTREPQG"
  },
  {
    "alias": "BTREPQI",
    "name": "V_BTREPQI"
  },
  {
    "alias": "BTREPQK",
    "name": "V_BTREPQK"
  },
  {
    "alias": "BTREPQN",
    "name": "V_BTREPQN"
  },
  {
    "alias": "BTREPQO",
    "name": "V_BTREPQO"
  },
  {
    "alias": "BTREPQP",
    "name": "V_BTREPQP"
  },
  {
    "alias": "BTREPQR",
    "name": "V_BTREPQR"
  },
  {
    "alias": "BTREPQU",
    "name": "V_BTREPQU"
  },
  {
    "alias": "BTREPQV",
    "name": "V_BTREPQV"
  },
  {
    "alias": "BTRESINEUV",
    "name": "V_BTRESINEUV"
  },
  {
    "alias": "BTRFRHR1",
    "name": "V_BTRFRHR1"
  },
  {
    "alias": "BTRFRHR2",
    "name": "V_BTRFRHR2"
  },
  {
    "alias": "BTRFRN1",
    "name": "V_BTRFRN1"
  },
  {
    "alias": "BTRFRN2",
    "name": "V_BTRFRN2"
  },
  {
    "alias": "BTRFRN3",
    "name": "V_BTRFRN3"
  },
  {
    "alias": "BTRNI",
    "name": "V_BTRNI"
  },
  {
    "alias": "BTRRCEL1",
    "name": "V_BTRRCEL1"
  },
  {
    "alias": "BTRRCEL2",
    "name": "V_BTRRCEL2"
  },
  {
    "alias": "BTRRCEL3",
    "name": "V_BTRRCEL3"
  },
  {
    "alias": "BTRRCEL4",
    "name": "V_BTRRCEL4"
  },
  {
    "alias": "BTSINFOR",
    "name": "V_BTSINFOR"
  },
  {
    "alias": "CALCULIR",
    "name": "V_CALCULIR"
  },
  {
    "alias": "CALCULMAJO",
    "name": "V_CALCULMAJO"
  },
  {
    "alias": "CDISANT",
    "name": "V_CDISANT"
  },
  {
    "alias": "CHRANT",
    "name": "V_CHRANT"
  },
  {
    "alias": "CODILIAD",
    "name": "V_CODILIAD"
  },
  {
    "alias": "CODPF",
    "name": "V_CODPF"
  },
  {
    "alias": "CODPF1728",
    "name": "V_CODPF1728"
  },
  {
    "alias": "CODPF1728CAP",
    "name": "V_CODPF1728CAP"
  },
  {
    "alias": "CODPF1728CDI",
    "name": "V_CODPF1728CDIS"
  },
  {
    "alias": "CODPF1728CHR",
    "name": "V_CODPF1728CHR"
  },
  {
    "alias": "CODPF1728CRP",
    "name": "V_CODPF1728CRP"
  },
  {
    "alias": "CODPF1728CSA",
    "name": "V_CODPF1728CSAL"
  },
  {
    "alias": "CODPF1728CVN",
    "name": "V_CODPF1728CVN"
  },
  {
    "alias": "CODPF1728GAI",
    "name": "V_CODPF1728GAIN"
  },
  {
    "alias": "CODPF1728ISF",
    "name": "V_CODPF1728ISF"
  },
  {
    "alias": "CODPF1728LOY",
    "name": "V_CODPF1728LOY"
  },
  {
    "alias": "CODPF1728RS1",
    "name": "V_CODPF1728RSE1"
  },
  {
    "alias": "CODPF1728RS2",
    "name": "V_CODPF1728RSE2"
  },
  {
    "alias": "CODPF1728RS3",
    "name": "V_CODPF1728RSE3"
  },
  {
    "alias": "CODPF1728RS4",
    "name": "V_CODPF1728RSE4"
  },
  {
    "alias": "CODPF1728RS5",
    "name": "V_CODPF1728RSE5"
  },
  {
    "alias": "CODPFC",
    "name": "V_CODPFC"
  },
  {
    "alias": "CODPFCAP",
    "name": "V_CODPFCAP"
  },
  {
    "alias": "CODPFCDIS",
    "name": "V_CODPFCDIS"
  },
  {
    "alias": "CODPFCSAL",
    "name": "V_CODPFCSAL"
  },
  {
    "alias": "CODPFGAIN",
    "name": "V_CODPFGAIN"
  },
  {
    "alias": "CODPFI",
    "name": "V_CODPFI"
  },
  {
    "alias": "CODPFICAP",
    "name": "V_CODPFICAP"
  },
  {
    "alias": "CODPFICDIS",
    "name": "V_CODPFICDIS"
  },
  {
    "alias": "CODPFICHR",
    "name": "V_CODPFICHR"
  },
  {
    "alias": "CODPFICRP",
    "name": "V_CODPFICRP"
  },
  {
    "alias": "CODPFICSAL",
    "name": "V_CODPFICSAL"
  },
  {
    "alias": "CODPFICVN",
    "name": "V_CODPFICVN"
  },
  {
    "alias": "CODPFIGAIN",
    "name": "V_CODPFIGAIN"
  },
  {
    "alias": "CODPFIISF",
    "name": "V_CODPFIISF"
  },
  {
    "alias": "CODPFILOY",
    "name": "V_CODPFILOY"
  },
  {
    "alias": "CODPFIRSE1",
    "name": "V_CODPFIRSE1"
  },
  {
    "alias": "CODPFIRSE2",
    "name": "V_CODPFIRSE2"
  },
  {
    "alias": "CODPFIRSE3",
    "name": "V_CODPFIRSE3"
  },
  {
    "alias": "CODPFIRSE4",
    "name": "V_CODPFIRSE4"
  },
  {
    "alias": "CODPFIRSE5",
    "name": "V_CODPFIRSE5"
  },
  {
    "alias": "CODPFISF",
    "name": "V_CODPFISF"
  },
  {
    "alias": "CODPFITAXA",
    "name": "V_CODPFITAXA"
  },
  {
    "alias": "CODPFLOY",
    "name": "V_CODPFLOY"
  },
  {
    "alias": "CODPFP",
    "name": "V_CODPFP"
  },
  {
    "alias": "CODPFR",
    "name": "V_CODPFR"
  },
  {
    "alias": "CODPFRSE1",
    "name": "V_CODPFRSE1"
  },
  {
    "alias": "CODPFRSE2",
    "name": "V_CODPFRSE2"
  },
  {
    "alias": "CODPFRSE3",
    "name": "V_CODPFRSE3"
  },
  {
    "alias": "CODPFRSE4",
    "name": "V_CODPFRSE4"
  },
  {
    "alias": "CSALANT",
    "name": "V_CSALANT"
  },
  {
    "alias": "CSANT",
    "name": "V_CSANT"
  },
  {
    "alias": "CVNANT",
    "name": "V_CVNANT"
  },
  {
    "alias": "DATISF",
    "name": "V_DATISF"
  },
  {
    "alias": "DIFTEOREEL",
    "name": "V_DIFTEOREEL"
  },
  {
    "alias": "ETCVL",
    "name": "V_ETCVL"
  },
  {
    "alias": "FORCA",
    "name": "V_FORCA"
  },
  {
    "alias": "FORPA",
    "name": "V_FORPA"
  },
  {
    "alias": "FORVA",
    "name": "V_FORVA"
  },
  {
    "alias": "GAINSALANT",
    "name": "V_GAINSALANT"
  },
  {
    "alias": "GLOANT",
    "name": "V_GLOANT"
  },
  {
    "alias": "IDANT",
    "name": "V_IDANT"
  },
  {
    "alias": "IDGLOANT",
    "name": "V_IDGLOANT"
  },
  {
    "alias": "IDRSEANT",
    "name": "V_IDRSEANT"
  },
  {
    "alias": "INDG",
    "name": "V_INDG"
  },
  {
    "alias": "INDRIB",
    "name": "V_INDRIB"
  },
  {
    "alias": "INDTEO",
    "name": "V_INDTEO"
  },
  {
    "alias": "IND_NAP",
    "name": "V_IND_NAP"
  },
  {
    "alias": "IND_TRAIT",
    "name": "V_IND_TRAIT"
  },
  {
    "alias": "IRPSANT",
    "name": "V_IRPSANT"
  },
  {
    "alias": "NAPTEO",
    "name": "V_NAPTEO"
  },
  {
    "alias": "NBCOD1728",
    "name": "V_NBCOD1728"
  },
  {
    "alias": "NBCOD1728CAP",
    "name": "V_NBCOD1728CAP"
  },
  {
    "alias": "NBCOD1728CDI",
    "name": "V_NBCOD1728CDIS"
  },
  {
    "alias": "NBCOD1728CHR",
    "name": "V_NBCOD1728CHR"
  },
  {
    "alias": "NBCOD1728CRP",
    "name": "V_NBCOD1728CRP"
  },
  {
    "alias": "NBCOD1728CSA",
    "name": "V_NBCOD1728CSAL"
  },
  {
    "alias": "NBCOD1728CVN",
    "name": "V_NBCOD1728CVN"
  },
  {
    "alias": "NBCOD1728GAI",
    "name": "V_NBCOD1728GAIN"
  },
  {
    "alias": "NBCOD1728GLO",
    "name": "V_NBCOD1728GLO"
  },
  {
    "alias": "NBCOD1728ISF",
    "name": "V_NBCOD1728ISF"
  },
  {
    "alias": "NBCOD1728LOY",
    "name": "V_NBCOD1728LOY"
  },
  {
    "alias": "NB1728RSE1",
    "name": "V_NBCOD1728RSE1"
  },
  {
    "alias": "NB1728RSE2",
    "name": "V_NBCOD1728RSE2"
  },
  {
    "alias": "NB1728RSE3",
    "name": "V_NBCOD1728RSE3"
  },
  {
    "alias": "NB1728RSE4",
    "name": "V_NBCOD1728RSE4"
  },
  {
    "alias": "NB1728RSE5",
    "name": "V_NBCOD1728RSE5"
  },
  {
    "alias": "NBCOD1758ACA",
    "name": "V_NBCOD1758ACAP"
  },
  {
    "alias": "NBCOD1758ACH",
    "name": "V_NBCOD1758ACHR"
  },
  {
    "alias": "NBCOD1758ACL",
    "name": "V_NBCOD1758ACL"
  },
  {
    "alias": "NBCOD1758AIR",
    "name": "V_NBCOD1758AIR"
  },
  {
    "alias": "NBCOD1758ATA",
    "name": "V_NBCOD1758ATA"
  },
  {
    "alias": "NBCOD1758CHR",
    "name": "V_NBCOD1758CHR"
  },
  {
    "alias": "NBCOD1758PCA",
    "name": "V_NBCOD1758PCAP"
  },
  {
    "alias": "NBCODC",
    "name": "V_NBCODC"
  },
  {
    "alias": "NBCODCDIS",
    "name": "V_NBCODCDIS"
  },
  {
    "alias": "NBCODCSAL",
    "name": "V_NBCODCSAL"
  },
  {
    "alias": "NBCODGAIN",
    "name": "V_NBCODGAIN"
  },
  {
    "alias": "NBCODI",
    "name": "V_NBCODI"
  },
  {
    "alias": "NBCODICAP",
    "name": "V_NBCODICAP"
  },
  {
    "alias": "NBCODICDIS",
    "name": "V_NBCODICDIS"
  },
  {
    "alias": "NBCODICHR",
    "name": "V_NBCODICHR"
  },
  {
    "alias": "NBCODICRP",
    "name": "V_NBCODICRP"
  },
  {
    "alias": "NBCODICSAL",
    "name": "V_NBCODICSAL"
  },
  {
    "alias": "NBCODICVN",
    "name": "V_NBCODICVN"
  },
  {
    "alias": "NBCODIGAIN",
    "name": "V_NBCODIGAIN"
  },
  {
    "alias": "NBCODIISF",
    "name": "V_NBCODIISF"
  },
  {
    "alias": "NBCODILOY",
    "name": "V_NBCODILOY"
  },
  {
    "alias": "NBCODIRSE1",
    "name": "V_NBCODIRSE1"
  },
  {
    "alias": "NBCODIRSE2",
    "name": "V_NBCODIRSE2"
  },
  {
    "alias": "NBCODIRSE3",
    "name": "V_NBCODIRSE3"
  },
  {
    "alias": "NBCODIRSE4",
    "name": "V_NBCODIRSE4"
  },
  {
    "alias": "NBCODIRSE5",
    "name": "V_NBCODIRSE5"
  },
  {
    "alias": "NBCODISF",
    "name": "V_NBCODISF"
  },
  {
    "alias": "NBCODITAXA",
    "name": "V_NBCODITAXA"
  },
  {
    "alias": "NBCODP",
    "name": "V_NBCODP"
  },
  {
    "alias": "NBCODR",
    "name": "V_NBCODR"
  },
  {
    "alias": "NBCODRSE1",
    "name": "V_NBCODRSE1"
  },
  {
    "alias": "NBCODRSE2",
    "name": "V_NBCODRSE2"
  },
  {
    "alias": "NBCODRSE3",
    "name": "V_NBCODRSE3"
  },
  {
    "alias": "NBCODRSE4",
    "name": "V_NBCODRSE4"
  },
  {
    "alias": "NEGACO",
    "name": "V_NEGACO"
  },
  {
    "alias": "NEGTEO",
    "name": "V_NEGTEO"
  },
  {
    "alias": "NIMPA",
    "name": "V_NIMPA"
  },
  {
    "alias": "NIMPAIR",
    "name": "V_NIMPAIR"
  },
  {
    "alias": "NONRESTANT",
    "name": "V_NONRESTANT"
  },
  {
    "alias": "NOTRAIT",
    "name": "V_NOTRAIT"
  },
  {
    "alias": "PCAPANT",
    "name": "V_PCAPANT"
  },
  {
    "alias": "PPEISF",
    "name": "V_PPEISF"
  },
  {
    "alias": "PSANT",
    "name": "V_PSANT"
  },
  {
    "alias": "RTEO12R",
    "name": "V_RCOMP"
  },
  {
    "alias": "RTEO11R",
    "name": "V_RCREAT"
  },
  {
    "alias": "RDANT",
    "name": "V_RDANT"
  },
  {
    "alias": "RTEO2R",
    "name": "V_RDIFAGRI"
  },
  {
    "alias": "RTEO14R",
    "name": "V_RDONS"
  },
  {
    "alias": "REGANT",
    "name": "V_REGANT"
  },
  {
    "alias": "REGCO",
    "name": "V_REGCO"
  },
  {
    "alias": "RENT1R",
    "name": "V_RENT1"
  },
  {
    "alias": "RENT10R",
    "name": "V_RENT10"
  },
  {
    "alias": "RENT11R",
    "name": "V_RENT11"
  },
  {
    "alias": "RENT12R",
    "name": "V_RENT12"
  },
  {
    "alias": "RENT13R",
    "name": "V_RENT13"
  },
  {
    "alias": "RENT14R",
    "name": "V_RENT14"
  },
  {
    "alias": "RENT15R",
    "name": "V_RENT15"
  },
  {
    "alias": "RENT16R",
    "name": "V_RENT16"
  },
  {
    "alias": "RENT17R",
    "name": "V_RENT17"
  },
  {
    "alias": "RENT18R",
    "name": "V_RENT18"
  },
  {
    "alias": "RENT19R",
    "name": "V_RENT19"
  },
  {
    "alias": "RENT2R",
    "name": "V_RENT2"
  },
  {
    "alias": "RENT20R",
    "name": "V_RENT20"
  },
  {
    "alias": "RENT21R",
    "name": "V_RENT21"
  },
  {
    "alias": "RENT22R",
    "name": "V_RENT22"
  },
  {
    "alias": "RENT23R",
    "name": "V_RENT23"
  },
  {
    "alias": "RENT24R",
    "name": "V_RENT24"
  },
  {
    "alias": "RENT25R",
    "name": "V_RENT25"
  },
  {
    "alias": "RENT26R",
    "name": "V_RENT26"
  },
  {
    "alias": "RENT27R",
    "name": "V_RENT27"
  },
  {
    "alias": "RENT29R",
    "name": "V_RENT29"
  },
  {
    "alias": "RENT3R",
    "name": "V_RENT3"
  },
  {
    "alias": "RENT30R",
    "name": "V_RENT30"
  },
  {
    "alias": "RENT31R",
    "name": "V_RENT31"
  },
  {
    "alias": "RENT32R",
    "name": "V_RENT32"
  },
  {
    "alias": "RENT33R",
    "name": "V_RENT33"
  },
  {
    "alias": "RENT34R",
    "name": "V_RENT34"
  },
  {
    "alias": "RENT35R",
    "name": "V_RENT35"
  },
  {
    "alias": "RENT36R",
    "name": "V_RENT36"
  },
  {
    "alias": "RENT37R",
    "name": "V_RENT37"
  },
  {
    "alias": "RENT38R",
    "name": "V_RENT38"
  },
  {
    "alias": "RENT39R",
    "name": "V_RENT39"
  },
  {
    "alias": "RENT4R",
    "name": "V_RENT4"
  },
  {
    "alias": "RENT40R",
    "name": "V_RENT40"
  },
  {
    "alias": "RENT41R",
    "name": "V_RENT41"
  },
  {
    "alias": "RENT42R",
    "name": "V_RENT42"
  },
  {
    "alias": "RENT5R",
    "name": "V_RENT5"
  },
  {
    "alias": "RENT6R",
    "name": "V_RENT6"
  },
  {
    "alias": "RENT7R",
    "name": "V_RENT7"
  },
  {
    "alias": "RENT8R",
    "name": "V_RENT8"
  },
  {
    "alias": "RENT9R",
    "name": "V_RENT9"
  },
  {
    "alias": "RENTJR",
    "name": "V_RENTJ"
  },
  {
    "alias": "RENTMR",
    "name": "V_RENTM"
  },
  {
    "alias": "RTEO3R",
    "name": "V_RFORET"
  },
  {
    "alias": "RTEO6R",
    "name": "V_RHEBE"
  },
  {
    "alias": "RTEO15R",
    "name": "V_RIDOMPROE3"
  },
  {
    "alias": "RTEO16R",
    "name": "V_RIDOMPROE4"
  },
  {
    "alias": "RLOC1R",
    "name": "V_RLOC1"
  },
  {
    "alias": "RLOC10R",
    "name": "V_RLOC10"
  },
  {
    "alias": "RLOC11R",
    "name": "V_RLOC11"
  },
  {
    "alias": "RLOC12R",
    "name": "V_RLOC12"
  },
  {
    "alias": "RLOC13R",
    "name": "V_RLOC13"
  },
  {
    "alias": "RLOC14R",
    "name": "V_RLOC14"
  },
  {
    "alias": "RLOC15R",
    "name": "V_RLOC15"
  },
  {
    "alias": "RLOC16R",
    "name": "V_RLOC16"
  },
  {
    "alias": "RLOC17R",
    "name": "V_RLOC17"
  },
  {
    "alias": "RLOC18R",
    "name": "V_RLOC18"
  },
  {
    "alias": "RLOC19R",
    "name": "V_RLOC19"
  },
  {
    "alias": "RLOC2R",
    "name": "V_RLOC2"
  },
  {
    "alias": "RLOC20R",
    "name": "V_RLOC20"
  },
  {
    "alias": "RLOC21R",
    "name": "V_RLOC21"
  },
  {
    "alias": "RLOC22R",
    "name": "V_RLOC22"
  },
  {
    "alias": "RLOC23R",
    "name": "V_RLOC23"
  },
  {
    "alias": "RLOC24R",
    "name": "V_RLOC24"
  },
  {
    "alias": "RLOC25R",
    "name": "V_RLOC25"
  },
  {
    "alias": "RLOC26R",
    "name": "V_RLOC26"
  },
  {
    "alias": "RLOC27R",
    "name": "V_RLOC27"
  },
  {
    "alias": "RLOC28R",
    "name": "V_RLOC28"
  },
  {
    "alias": "RLOC29R",
    "name": "V_RLOC29"
  },
  {
    "alias": "RLOC3R",
    "name": "V_RLOC3"
  },
  {
    "alias": "RLOC35R",
    "name": "V_RLOC35"
  },
  {
    "alias": "RLOC36R",
    "name": "V_RLOC36"
  },
  {
    "alias": "RLOC37R",
    "name": "V_RLOC37"
  },
  {
    "alias": "RLOC38R",
    "name": "V_RLOC38"
  },
  {
    "alias": "RLOC39R",
    "name": "V_RLOC39"
  },
  {
    "alias": "RLOC4R",
    "name": "V_RLOC4"
  },
  {
    "alias": "RLOC40R",
    "name": "V_RLOC40"
  },
  {
    "alias": "RLOC41R",
    "name": "V_RLOC41"
  },
  {
    "alias": "RLOC42R",
    "name": "V_RLOC42"
  },
  {
    "alias": "RLOC43R",
    "name": "V_RLOC43"
  },
  {
    "alias": "RLOC44R",
    "name": "V_RLOC44"
  },
  {
    "alias": "RLOC5R",
    "name": "V_RLOC5"
  },
  {
    "alias": "RLOC6R",
    "name": "V_RLOC6"
  },
  {
    "alias": "RLOC7R",
    "name": "V_RLOC7"
  },
  {
    "alias": "RLOC8R",
    "name": "V_RLOC8"
  },
  {
    "alias": "RLOC9R",
    "name": "V_RLOC9"
  },
  {
    "alias": "RLOG1R",
    "name": "V_RLOG1"
  },
  {
    "alias": "RLOG10R",
    "name": "V_RLOG10"
  },
  {
    "alias": "RLOG12R",
    "name": "V_RLOG12"
  },
  {
    "alias": "RLOG2R",
    "name": "V_RLOG2"
  },
  {
    "alias": "RLOG3R",
    "name": "V_RLOG3"
  },
  {
    "alias": "RLOG4R",
    "name": "V_RLOG4"
  },
  {
    "alias": "RLOG5R",
    "name": "V_RLOG5"
  },
  {
    "alias": "RLOG6R",
    "name": "V_RLOG6"
  },
  {
    "alias": "RLOG7R",
    "name": "V_RLOG7"
  },
  {
    "alias": "RLOG8R",
    "name": "V_RLOG8"
  },
  {
    "alias": "RTEO17R",
    "name": "V_RNOUV"
  },
  {
    "alias": "ROLCSG",
    "name": "V_ROLCSG"
  },
  {
    "alias": "RTEO1R",
    "name": "V_RREPA"
  },
  {
    "alias": "RTEO13R",
    "name": "V_RRETU"
  },
  {
    "alias": "RTEO5R",
    "name": "V_RRPRESCOMP"
  },
  {
    "alias": "RSE1ANT",
    "name": "V_RSE1ANT"
  },
  {
    "alias": "RSE2ANT",
    "name": "V_RSE2ANT"
  },
  {
    "alias": "RSE3ANT",
    "name": "V_RSE3ANT"
  },
  {
    "alias": "RSE4ANT",
    "name": "V_RSE4ANT"
  },
  {
    "alias": "RSE5ANT",
    "name": "V_RSE5ANT"
  },
  {
    "alias": "RSOC1R",
    "name": "V_RSOC1"
  },
  {
    "alias": "RSOC10R",
    "name": "V_RSOC10"
  },
  {
    "alias": "RSOC11R",
    "name": "V_RSOC11"
  },
  {
    "alias": "RSOC12R",
    "name": "V_RSOC12"
  },
  {
    "alias": "RSOC13R",
    "name": "V_RSOC13"
  },
  {
    "alias": "RSOC14R",
    "name": "V_RSOC14"
  },
  {
    "alias": "RSOC15R",
    "name": "V_RSOC15"
  },
  {
    "alias": "RSOC16R",
    "name": "V_RSOC16"
  },
  {
    "alias": "RSOC17R",
    "name": "V_RSOC17"
  },
  {
    "alias": "RSOC18R",
    "name": "V_RSOC18"
  },
  {
    "alias": "RSOC19R",
    "name": "V_RSOC19"
  },
  {
    "alias": "RSOC2R",
    "name": "V_RSOC2"
  },
  {
    "alias": "RSOC20R",
    "name": "V_RSOC20"
  },
  {
    "alias": "RSOC3R",
    "name": "V_RSOC3"
  },
  {
    "alias": "RSOC4R",
    "name": "V_RSOC4"
  },
  {
    "alias": "RSOC5R",
    "name": "V_RSOC5"
  },
  {
    "alias": "RSOC6R",
    "name": "V_RSOC6"
  },
  {
    "alias": "RSOC7R",
    "name": "V_RSOC7"
  },
  {
    "alias": "RSOC8R",
    "name": "V_RSOC8"
  },
  {
    "alias": "RSOC9R",
    "name": "V_RSOC9"
  },
  {
    "alias": "RTEO4R",
    "name": "V_RSOCREPR"
  },
  {
    "alias": "RTEO7R",
    "name": "V_RSURV"
  },
  {
    "alias": "RTEO9R",
    "name": "V_RTOUHOTRTEO"
  },
  {
    "alias": "RTEO10R",
    "name": "V_RTOUREPATEO"
  },
  {
    "alias": "RTEO8R",
    "name": "V_RTOURREPTEO"
  },
  {
    "alias": "4BZ",
    "name": "V_SPE2044"
  },
  {
    "alias": "TAXANT",
    "name": "V_TAXANT"
  },
  {
    "alias": "TAXLOYANT",
    "name": "V_TAXLOYANT"
  },
  {
    "alias": "TOTIRANT",
    "name": "V_TOTIRANT"
  },
  {
    "alias": "TRCT",
    "name": "V_TRCT"
  },
  {
    "alias": "VAR7WZ",
    "name": "V_VAR7WZ"
  },
  {
    "alias": "ZDC",
    "name": "V_ZDC"
  },
  {
    "alias": "1EY",
    "name": "XETRANC"
  },
  {
    "alias": "1DY",
    "name": "XETRANV"
  },
  {
    "alias": "5UF",
    "name": "XHONOAAC"
  },
  {
    "alias": "5VF",
    "name": "XHONOAAP"
  },
  {
    "alias": "5TF",
    "name": "XHONOAAV"
  },
  {
    "alias": "5UI",
    "name": "XHONOC"
  },
  {
    "alias": "5VI",
    "name": "XHONOP"
  },
  {
    "alias": "5TI",
    "name": "XHONOV"
  },
  {
    "alias": "5UH",
    "name": "XSPENPC"
  },
  {
    "alias": "5VH",
    "name": "XSPENPP"
  },
  {
    "alias": "5TH",
    "name": "XSPENPV"
  },
  {
    "alias": "8YQ",
    "name": "ZONEANTEK"
  }
]